{"VERSION":"0.0.7","engineVersion":null,"uuidToPath":{"0946f4R-130a1eE-f1c506S-9de1d3R":{"path":"09/0946f4R-130a1eE-f1c506S-9de1d3R.platform","tempPath":"","meta":{"uuid":"0946f4R-130a1eE-f1c506S-9de1d3R","importSettings":{"textureData":{"data":{"width":256,"height":256,"sRGB":true,"needPremultiplyAlpha":false,"useMipmap":true,"mipmap":9,"wrapU":1,"wrapV":1,"filterMode":2,"pixelFormat":2,"anisoLevel":1},"editorInfo":{"assetVersion":2,"enableCompress":true}},"__localId":{"texture2d":1},"metaMTime":1604661026018,"inheritGroupId":true,"groupId":"","isEntries":"false","recursiveSetEntries":true,"isPackInBuildIn":"false"},"ver":"1","dependencies":["1f1b68R-1fbe93E-854effS-d9999aR","34d886R-e6164cE-c15166S-24aac4R","8e0dd0R-4ff909E-f653d6S-c62450R","392a7eR-ee9715E-73f0d7S-bb1836R"],"fileDependencies":[],"size":167,"srcHash":"204673d3c55dad39f346bf2f21458d11","hash":"204673d3c55dad39f346bf2f21458d11","service":"texture2dService"}},"34d886R-e6164cE-c15166S-24aac4R":{"path":"34/34d886R-e6164cE-c15166S-24aac4R.texture2d","tempPath":"","meta":{"uuid":"34d886R-e6164cE-c15166S-24aac4R","importSettings":{},"ver":"1","dependencies":[],"fileDependencies":["276d45F-0f43daI-cb849dL-25ca19E"],"size":220,"hash":"90804198f8ebd40c69ff00fb4b9679c9","srcHash":"90804198f8ebd40c69ff00fb4b9679c9","service":"texture2dService"}},"276d45F-0f43daI-cb849dL-25ca19E":{"path":"27/276d45F-0f43daI-cb849dL-25ca19E.etc2.ktx","tempPath":"","meta":{"uuid":"276d45F-0f43daI-cb849dL-25ca19E","importSettings":{"relatedSrcUuid":"5365ffF-bf862fI-d1d566L-19361aE"},"ver":"1","dependencies":[],"fileDependencies":[],"size":87540,"srcHash":"0c35bd980ee278a7244d853ddf1cf52f","hash":"0c35bd980ee278a7244d853ddf1cf52f","service":"texture2dService"}},"8e0dd0R-4ff909E-f653d6S-c62450R":{"path":"8e/8e0dd0R-4ff909E-f653d6S-c62450R.texture2d","tempPath":"","meta":{"uuid":"8e0dd0R-4ff909E-f653d6S-c62450R","importSettings":{},"ver":"1","dependencies":[],"fileDependencies":["2f5eceF-4686adI-3017f2L-101812E"],"size":220,"hash":"7ed9054548d0461cd20a4abab56f3e88","srcHash":"7ed9054548d0461cd20a4abab56f3e88","service":"texture2dService"}},"2f5eceF-4686adI-3017f2L-101812E":{"path":"2f/2f5eceF-4686adI-3017f2L-101812E.astc.ktx","tempPath":"","meta":{"uuid":"2f5eceF-4686adI-3017f2L-101812E","importSettings":{"relatedSrcUuid":"5365ffF-bf862fI-d1d566L-19361aE"},"ver":"1","dependencies":[],"fileDependencies":[],"size":22020,"srcHash":"094a57c1f4228216006b68053a9e2990","hash":"094a57c1f4228216006b68053a9e2990","service":"texture2dService"}},"392a7eR-ee9715E-73f0d7S-bb1836R":{"path":"39/392a7eR-ee9715E-73f0d7S-bb1836R.texture2d","tempPath":"","meta":{"uuid":"392a7eR-ee9715E-73f0d7S-bb1836R","importSettings":{},"ver":"1","dependencies":[],"fileDependencies":["450db9F-e8b9d2I-a21aacL-9f186fE"],"size":220,"hash":"5662656d70e559f65bc083b20847e4bf","srcHash":"5662656d70e559f65bc083b20847e4bf","service":"texture2dService"}},"450db9F-e8b9d2I-a21aacL-9f186fE":{"path":"45/450db9F-e8b9d2I-a21aacL-9f186fE.pvr.pvr","tempPath":"","meta":{"uuid":"450db9F-e8b9d2I-a21aacL-9f186fE","importSettings":{"relatedSrcUuid":"5365ffF-bf862fI-d1d566L-19361aE"},"ver":"1","dependencies":[],"fileDependencies":[],"size":43843,"srcHash":"1113681f6b0ad57d10f1acd3fda9aef2","hash":"1113681f6b0ad57d10f1acd3fda9aef2","service":"texture2dService"}},"17bac2R-696b9eE-cce134S-b706b8R":{"path":"17/17bac2R-696b9eE-cce134S-b706b8R.platform","tempPath":"","meta":{"uuid":"17bac2R-696b9eE-cce134S-b706b8R","importSettings":{"textureData":{"data":{"width":128,"height":128,"sRGB":true,"needPremultiplyAlpha":false,"useMipmap":true,"mipmap":8,"wrapU":1,"wrapV":1,"filterMode":2,"pixelFormat":2,"anisoLevel":1},"editorInfo":{"assetVersion":2,"enableCompress":true}},"__localId":{"texture2d":1},"metaMTime":1604661025975,"inheritGroupId":true,"groupId":"","isEntries":"false","recursiveSetEntries":true,"isPackInBuildIn":"false"},"ver":"1","dependencies":["c5d410R-b8a879E-2599bcS-5680ddR","8a5cb1R-c9f08bE-d563f5S-c98e85R","999cbdR-ad5960E-82d9a3S-d3a50fR","80254eR-9b909aE-1e5ad2S-365ecbR"],"fileDependencies":[],"size":167,"srcHash":"40f548f0a52bd138e3165f6c13c2fc45","hash":"40f548f0a52bd138e3165f6c13c2fc45","service":"texture2dService"}},"8a5cb1R-c9f08bE-d563f5S-c98e85R":{"path":"8a/8a5cb1R-c9f08bE-d563f5S-c98e85R.texture2d","tempPath":"","meta":{"uuid":"8a5cb1R-c9f08bE-d563f5S-c98e85R","importSettings":{},"ver":"1","dependencies":[],"fileDependencies":["e6e745F-cc8285I-3fe260L-335e63E"],"size":220,"hash":"1db0f883fefb1545fdc25034dec1fc4a","srcHash":"1db0f883fefb1545fdc25034dec1fc4a","service":"texture2dService"}},"e6e745F-cc8285I-3fe260L-335e63E":{"path":"e6/e6e745F-cc8285I-3fe260L-335e63E.etc2.ktx","tempPath":"","meta":{"uuid":"e6e745F-cc8285I-3fe260L-335e63E","importSettings":{"relatedSrcUuid":"0a74a6F-e91e17I-33a59bL-16e923E"},"ver":"1","dependencies":[],"fileDependencies":[],"size":22000,"srcHash":"6f37b96b4cfb679f491e39834692384d","hash":"6f37b96b4cfb679f491e39834692384d","service":"texture2dService"}},"999cbdR-ad5960E-82d9a3S-d3a50fR":{"path":"99/999cbdR-ad5960E-82d9a3S-d3a50fR.texture2d","tempPath":"","meta":{"uuid":"999cbdR-ad5960E-82d9a3S-d3a50fR","importSettings":{},"ver":"1","dependencies":[],"fileDependencies":["c723ddF-7baec8I-db9fb0L-2a0bb3E"],"size":220,"hash":"b63381ec9e41843c3378dc078ba99abd","srcHash":"b63381ec9e41843c3378dc078ba99abd","service":"texture2dService"}},"c723ddF-7baec8I-db9fb0L-2a0bb3E":{"path":"c7/c723ddF-7baec8I-db9fb0L-2a0bb3E.astc.ktx","tempPath":"","meta":{"uuid":"c723ddF-7baec8I-db9fb0L-2a0bb3E","importSettings":{"relatedSrcUuid":"0a74a6F-e91e17I-33a59bL-16e923E"},"ver":"1","dependencies":[],"fileDependencies":[],"size":5632,"srcHash":"0310c56284b18d64247469ce267d23f0","hash":"0310c56284b18d64247469ce267d23f0","service":"texture2dService"}},"80254eR-9b909aE-1e5ad2S-365ecbR":{"path":"80/80254eR-9b909aE-1e5ad2S-365ecbR.texture2d","tempPath":"","meta":{"uuid":"80254eR-9b909aE-1e5ad2S-365ecbR","importSettings":{},"ver":"1","dependencies":[],"fileDependencies":["0e7f46F-b0e5fdI-747573L-72be4dE"],"size":220,"hash":"c78ad542d9e52914ead4860d53cc7eb1","srcHash":"c78ad542d9e52914ead4860d53cc7eb1","service":"texture2dService"}},"0e7f46F-b0e5fdI-747573L-72be4dE":{"path":"0e/0e7f46F-b0e5fdI-747573L-72be4dE.pvr.pvr","tempPath":"","meta":{"uuid":"0e7f46F-b0e5fdI-747573L-72be4dE","importSettings":{"relatedSrcUuid":"0a74a6F-e91e17I-33a59bL-16e923E"},"ver":"1","dependencies":[],"fileDependencies":[],"size":11075,"srcHash":"f03fbd40924aba9850d6285dc7d30e4b","hash":"f03fbd40924aba9850d6285dc7d30e4b","service":"texture2dService"}},"1aa5b1R-f50db4E-88d79fS-cf7426R":{"path":"1a/1aa5b1R-f50db4E-88d79fS-cf7426R.platform","tempPath":"","meta":{"uuid":"1aa5b1R-f50db4E-88d79fS-cf7426R","importSettings":{"textureData":{"data":{"width":128,"height":128,"sRGB":true,"needPremultiplyAlpha":false,"useMipmap":true,"mipmap":8,"wrapU":1,"wrapV":1,"filterMode":2,"pixelFormat":2,"anisoLevel":1},"editorInfo":{"assetVersion":2,"enableCompress":true}},"__localId":{"texture2d":1},"metaMTime":1604661025991,"inheritGroupId":true,"groupId":"","isEntries":"false","recursiveSetEntries":true,"isPackInBuildIn":"false"},"ver":"1","dependencies":["a1c543R-06b0b6E-2320a5S-ea08fbR","0c7562R-b284c5E-b51c5cS-9cbd3bR","b9616aR-6cebf1E-2132adS-de9adbR","7d2026R-5356bbE-bf0b17S-93f620R"],"fileDependencies":[],"size":167,"srcHash":"04bd7e268b4467357ddffac7d3028842","hash":"04bd7e268b4467357ddffac7d3028842","service":"texture2dService"}},"0c7562R-b284c5E-b51c5cS-9cbd3bR":{"path":"0c/0c7562R-b284c5E-b51c5cS-9cbd3bR.texture2d","tempPath":"","meta":{"uuid":"0c7562R-b284c5E-b51c5cS-9cbd3bR","importSettings":{},"ver":"1","dependencies":[],"fileDependencies":["7a2324F-c63dceI-dec50eL-399946E"],"size":220,"hash":"ca30a223967fb2c2c491c8b6062c978f","srcHash":"ca30a223967fb2c2c491c8b6062c978f","service":"texture2dService"}},"7a2324F-c63dceI-dec50eL-399946E":{"path":"7a/7a2324F-c63dceI-dec50eL-399946E.etc2.ktx","tempPath":"","meta":{"uuid":"7a2324F-c63dceI-dec50eL-399946E","importSettings":{"relatedSrcUuid":"bc8d98F-b4e368I-92bb6dL-8d40d5E"},"ver":"1","dependencies":[],"fileDependencies":[],"size":22000,"srcHash":"0ee3d366480997bab582300908d5ea95","hash":"0ee3d366480997bab582300908d5ea95","service":"texture2dService"}},"b9616aR-6cebf1E-2132adS-de9adbR":{"path":"b9/b9616aR-6cebf1E-2132adS-de9adbR.texture2d","tempPath":"","meta":{"uuid":"b9616aR-6cebf1E-2132adS-de9adbR","importSettings":{},"ver":"1","dependencies":[],"fileDependencies":["8176e4F-aa0003I-be3d6dL-953439E"],"size":220,"hash":"4acc08e8b18fd716e7626a405bc082fc","srcHash":"4acc08e8b18fd716e7626a405bc082fc","service":"texture2dService"}},"8176e4F-aa0003I-be3d6dL-953439E":{"path":"81/8176e4F-aa0003I-be3d6dL-953439E.astc.ktx","tempPath":"","meta":{"uuid":"8176e4F-aa0003I-be3d6dL-953439E","importSettings":{"relatedSrcUuid":"bc8d98F-b4e368I-92bb6dL-8d40d5E"},"ver":"1","dependencies":[],"fileDependencies":[],"size":5632,"srcHash":"a814679078b2b966607b614e9cf8bab0","hash":"a814679078b2b966607b614e9cf8bab0","service":"texture2dService"}},"7d2026R-5356bbE-bf0b17S-93f620R":{"path":"7d/7d2026R-5356bbE-bf0b17S-93f620R.texture2d","tempPath":"","meta":{"uuid":"7d2026R-5356bbE-bf0b17S-93f620R","importSettings":{},"ver":"1","dependencies":[],"fileDependencies":["a60523F-d0a60bI-7923acL-6543e9E"],"size":220,"hash":"af1bbf970deac9723b1007807cdc6228","srcHash":"af1bbf970deac9723b1007807cdc6228","service":"texture2dService"}},"a60523F-d0a60bI-7923acL-6543e9E":{"path":"a6/a60523F-d0a60bI-7923acL-6543e9E.pvr.pvr","tempPath":"","meta":{"uuid":"a60523F-d0a60bI-7923acL-6543e9E","importSettings":{"relatedSrcUuid":"bc8d98F-b4e368I-92bb6dL-8d40d5E"},"ver":"1","dependencies":[],"fileDependencies":[],"size":11075,"srcHash":"31bad67944fad02f5fb2069567d0b0ce","hash":"31bad67944fad02f5fb2069567d0b0ce","service":"texture2dService"}},"1af810R-9af831E-5d3ff5S-88d43dR":{"path":"1a/1af810R-9af831E-5d3ff5S-88d43dR.platform","tempPath":"","meta":{"uuid":"1af810R-9af831E-5d3ff5S-88d43dR","importSettings":{"textureData":{"data":{"width":256,"height":256,"sRGB":true,"needPremultiplyAlpha":false,"useMipmap":true,"mipmap":9,"wrapU":1,"wrapV":1,"filterMode":2,"pixelFormat":2,"anisoLevel":1},"editorInfo":{"assetVersion":2,"enableCompress":true}},"__localId":{"texture2d":1},"metaMTime":1604661025956,"inheritGroupId":true,"groupId":"","isEntries":"false","recursiveSetEntries":true,"isPackInBuildIn":"false"},"ver":"1","dependencies":["23502aR-daafd4E-57b165S-101c8bR","37bef8R-951861E-42a545S-5d56d3R","bc80dbR-5a4486E-3a5ed5S-76fbd4R","bdb348R-98ed66E-e047e3S-a9e26bR"],"fileDependencies":[],"size":167,"srcHash":"76d22685972e7ec16d6fdb4f32bb7ec2","hash":"76d22685972e7ec16d6fdb4f32bb7ec2","service":"texture2dService"}},"37bef8R-951861E-42a545S-5d56d3R":{"path":"37/37bef8R-951861E-42a545S-5d56d3R.texture2d","tempPath":"","meta":{"uuid":"37bef8R-951861E-42a545S-5d56d3R","importSettings":{},"ver":"1","dependencies":[],"fileDependencies":["27085cF-2439f0I-e0d3c3L-93f348E"],"size":220,"hash":"7a4aa23916e9eda90e9d5792f306cbc0","srcHash":"7a4aa23916e9eda90e9d5792f306cbc0","service":"texture2dService"}},"27085cF-2439f0I-e0d3c3L-93f348E":{"path":"27/27085cF-2439f0I-e0d3c3L-93f348E.etc2.ktx","tempPath":"","meta":{"uuid":"27085cF-2439f0I-e0d3c3L-93f348E","importSettings":{"relatedSrcUuid":"d73f52F-772699I-9ae934L-30c2e1E"},"ver":"1","dependencies":[],"fileDependencies":[],"size":87540,"srcHash":"e88b9782b56b749f816a067d02865c62","hash":"e88b9782b56b749f816a067d02865c62","service":"texture2dService"}},"bc80dbR-5a4486E-3a5ed5S-76fbd4R":{"path":"bc/bc80dbR-5a4486E-3a5ed5S-76fbd4R.texture2d","tempPath":"","meta":{"uuid":"bc80dbR-5a4486E-3a5ed5S-76fbd4R","importSettings":{},"ver":"1","dependencies":[],"fileDependencies":["fa3527F-b5f120I-c84325L-73c3eaE"],"size":220,"hash":"3e16dcdd74c2ac9f5451d03489cf12a9","srcHash":"3e16dcdd74c2ac9f5451d03489cf12a9","service":"texture2dService"}},"fa3527F-b5f120I-c84325L-73c3eaE":{"path":"fa/fa3527F-b5f120I-c84325L-73c3eaE.astc.ktx","tempPath":"","meta":{"uuid":"fa3527F-b5f120I-c84325L-73c3eaE","importSettings":{"relatedSrcUuid":"d73f52F-772699I-9ae934L-30c2e1E"},"ver":"1","dependencies":[],"fileDependencies":[],"size":22020,"srcHash":"907df9690f572f2815ca7be2eb45697b","hash":"907df9690f572f2815ca7be2eb45697b","service":"texture2dService"}},"bdb348R-98ed66E-e047e3S-a9e26bR":{"path":"bd/bdb348R-98ed66E-e047e3S-a9e26bR.texture2d","tempPath":"","meta":{"uuid":"bdb348R-98ed66E-e047e3S-a9e26bR","importSettings":{},"ver":"1","dependencies":[],"fileDependencies":["3f58d8F-c43a42I-673793L-e16d3cE"],"size":220,"hash":"f667cec61f3e404d48ecd0c855f5f671","srcHash":"f667cec61f3e404d48ecd0c855f5f671","service":"texture2dService"}},"3f58d8F-c43a42I-673793L-e16d3cE":{"path":"3f/3f58d8F-c43a42I-673793L-e16d3cE.pvr.pvr","tempPath":"","meta":{"uuid":"3f58d8F-c43a42I-673793L-e16d3cE","importSettings":{"relatedSrcUuid":"d73f52F-772699I-9ae934L-30c2e1E"},"ver":"1","dependencies":[],"fileDependencies":[],"size":43843,"srcHash":"548d070874c1e50052420b31fb8aa7cd","hash":"548d070874c1e50052420b31fb8aa7cd","service":"texture2dService"}},"342acdR-3ac821E-9f6ae5S-63fba6R":{"path":"34/342acdR-3ac821E-9f6ae5S-63fba6R.platform","tempPath":"","meta":{"uuid":"342acdR-3ac821E-9f6ae5S-63fba6R","importSettings":{"textureData":{"data":{"width":512,"height":512,"sRGB":true,"needPremultiplyAlpha":false,"useMipmap":true,"mipmap":10,"wrapU":1,"wrapV":1,"filterMode":2,"pixelFormat":2,"anisoLevel":1},"editorInfo":{"assetVersion":2,"enableCompress":true}},"__localId":{"texture2d":1},"metaMTime":1604661026000,"inheritGroupId":true,"groupId":"","isEntries":"false","recursiveSetEntries":true,"isPackInBuildIn":"false"},"ver":"1","dependencies":["3e39f0R-af5af9E-882fb4S-35be2eR","094169R-f0c296E-34fbd7S-cb4a94R","ca1747R-5aae59E-6613e3S-04c8c6R","181d82R-33e229E-b73c33S-46c84bR","788d11R-558238E-1d4de2S-f8ffdbR"],"fileDependencies":[],"size":208,"srcHash":"8916866de7c209a31a2b4281bcd5cd3f","hash":"8916866de7c209a31a2b4281bcd5cd3f","service":"texture2dService"}},"094169R-f0c296E-34fbd7S-cb4a94R":{"path":"09/094169R-f0c296E-34fbd7S-cb4a94R.texture2d","tempPath":"","meta":{"uuid":"094169R-f0c296E-34fbd7S-cb4a94R","importSettings":{},"ver":"1","dependencies":[],"fileDependencies":["b45f56F-f5af41I-0226bdL-213af2E"],"size":221,"hash":"12a6691246d77a0941c88014c7fd14bd","srcHash":"12a6691246d77a0941c88014c7fd14bd","service":"texture2dService"}},"b45f56F-f5af41I-0226bdL-213af2E":{"path":"b4/b45f56F-f5af41I-0226bdL-213af2E.etc2.ktx","tempPath":"","meta":{"uuid":"b45f56F-f5af41I-0226bdL-213af2E","importSettings":{"relatedSrcUuid":"4eabb1F-a6d6acI-18916bL-c22216E"},"ver":"1","dependencies":[],"fileDependencies":[],"size":174912,"srcHash":"3c9281a8547828e087b1b917d4b1942f","hash":"3c9281a8547828e087b1b917d4b1942f","service":"texture2dService"}},"ca1747R-5aae59E-6613e3S-04c8c6R":{"path":"ca/ca1747R-5aae59E-6613e3S-04c8c6R.texture2d","tempPath":"","meta":{"uuid":"ca1747R-5aae59E-6613e3S-04c8c6R","importSettings":{},"ver":"1","dependencies":[],"fileDependencies":["8a7fe7F-42c2fdI-d75d88L-a894f4E"],"size":221,"hash":"fbf853a78bf4871538c5be3e7540c6ed","srcHash":"fbf853a78bf4871538c5be3e7540c6ed","service":"texture2dService"}},"8a7fe7F-42c2fdI-d75d88L-a894f4E":{"path":"8a/8a7fe7F-42c2fdI-d75d88L-a894f4E.astc.ktx","tempPath":"","meta":{"uuid":"8a7fe7F-42c2fdI-d75d88L-a894f4E","importSettings":{"relatedSrcUuid":"4eabb1F-a6d6acI-18916bL-c22216E"},"ver":"1","dependencies":[],"fileDependencies":[],"size":87560,"srcHash":"cd0a41dd4fd43784fb2062613e1c722a","hash":"cd0a41dd4fd43784fb2062613e1c722a","service":"texture2dService"}},"181d82R-33e229E-b73c33S-46c84bR":{"path":"18/181d82R-33e229E-b73c33S-46c84bR.texture2d","tempPath":"","meta":{"uuid":"181d82R-33e229E-b73c33S-46c84bR","importSettings":{},"ver":"1","dependencies":[],"fileDependencies":["dcba42F-3a8329I-9231d0L-711307E"],"size":221,"hash":"b744378fef54c3d18b2f02e944f157a1","srcHash":"b744378fef54c3d18b2f02e944f157a1","service":"texture2dService"}},"dcba42F-3a8329I-9231d0L-711307E":{"path":"dc/dcba42F-3a8329I-9231d0L-711307E.pvr.pvr","tempPath":"","meta":{"uuid":"dcba42F-3a8329I-9231d0L-711307E","importSettings":{"relatedSrcUuid":"4eabb1F-a6d6acI-18916bL-c22216E"},"ver":"1","dependencies":[],"fileDependencies":[],"size":174915,"srcHash":"d0c96e2b85e9a46ee41fd1df138067e4","hash":"d0c96e2b85e9a46ee41fd1df138067e4","service":"texture2dService"}},"788d11R-558238E-1d4de2S-f8ffdbR":{"path":"78/788d11R-558238E-1d4de2S-f8ffdbR.texture2d","tempPath":"","meta":{"uuid":"788d11R-558238E-1d4de2S-f8ffdbR","importSettings":{},"ver":"1","dependencies":[],"fileDependencies":["0d0331F-b8d37aI-0ab60dL-8831acE"],"size":221,"hash":"d308157f1cc48bad9d6d1133a987db57","srcHash":"d308157f1cc48bad9d6d1133a987db57","service":"texture2dService"}},"0d0331F-b8d37aI-0ab60dL-8831acE":{"path":"0d/0d0331F-b8d37aI-0ab60dL-8831acE.etc1.ktx","tempPath":"","meta":{"uuid":"0d0331F-b8d37aI-0ab60dL-8831acE","importSettings":{"relatedSrcUuid":"4eabb1F-a6d6acI-18916bL-c22216E"},"ver":"1","dependencies":[],"fileDependencies":[],"size":174912,"srcHash":"f045f8d4587a4c4fee5ac22b384ece62","hash":"f045f8d4587a4c4fee5ac22b384ece62","service":"texture2dService"}},"4a50ccR-e2e892E-7347deS-4483d1R":{"path":"4a/4a50ccR-e2e892E-7347deS-4483d1R.platform","tempPath":"","meta":{"uuid":"4a50ccR-e2e892E-7347deS-4483d1R","importSettings":{"textureData":{"data":{"width":400,"height":400,"sRGB":true,"needPremultiplyAlpha":false,"useMipmap":false,"mipmap":1,"wrapU":2,"wrapV":2,"filterMode":0,"pixelFormat":2,"anisoLevel":1,"wrapS":2,"wrapT":2},"editorInfo":{"assetVersion":2,"enableCompress":true}},"__localId":{"texture2d":1},"metaMTime":1604661026087,"inheritGroupId":true,"groupId":"","isEntries":"false","recursiveSetEntries":true,"isPackInBuildIn":"false"},"ver":"1","dependencies":["59b5dcR-544364E-bb2413S-f769c0R","2acb11R-2d0869E-cf106bS-081a47R","f93336R-c96589E-6c6d34S-b16828R"],"fileDependencies":[],"size":127,"srcHash":"ca21dcef2be075f6e6666fb94b058299","hash":"ca21dcef2be075f6e6666fb94b058299","service":"texture2dService"}},"2acb11R-2d0869E-cf106bS-081a47R":{"path":"2a/2acb11R-2d0869E-cf106bS-081a47R.texture2d","tempPath":"","meta":{"uuid":"2acb11R-2d0869E-cf106bS-081a47R","importSettings":{},"ver":"1","dependencies":[],"fileDependencies":["23a353F-e34af1I-6afd35L-c4bea0E"],"size":241,"hash":"4f0bf33af74f84083cc362f56a2e50dc","srcHash":"4f0bf33af74f84083cc362f56a2e50dc","service":"texture2dService"}},"23a353F-e34af1I-6afd35L-c4bea0E":{"path":"23/23a353F-e34af1I-6afd35L-c4bea0E.etc2.ktx","tempPath":"","meta":{"uuid":"23a353F-e34af1I-6afd35L-c4bea0E","importSettings":{"relatedSrcUuid":"8d5288F-6280aeI-39e031L-a83085E"},"ver":"1","dependencies":[],"fileDependencies":[],"size":160100,"srcHash":"707588bd2f5407612e1a927a5720f639","hash":"707588bd2f5407612e1a927a5720f639","service":"texture2dService"}},"f93336R-c96589E-6c6d34S-b16828R":{"path":"f9/f93336R-c96589E-6c6d34S-b16828R.texture2d","tempPath":"","meta":{"uuid":"f93336R-c96589E-6c6d34S-b16828R","importSettings":{},"ver":"1","dependencies":[],"fileDependencies":["8a372cF-bbf967I-603cc6L-723ba9E"],"size":241,"hash":"cc32e205e29fe0c6af6204281b66c3df","srcHash":"cc32e205e29fe0c6af6204281b66c3df","service":"texture2dService"}},"8a372cF-bbf967I-603cc6L-723ba9E":{"path":"8a/8a372cF-bbf967I-603cc6L-723ba9E.astc.ktx","tempPath":"","meta":{"uuid":"8a372cF-bbf967I-603cc6L-723ba9E","importSettings":{"relatedSrcUuid":"8d5288F-6280aeI-39e031L-a83085E"},"ver":"1","dependencies":[],"fileDependencies":[],"size":40100,"srcHash":"750d3c182547aad3a75b74326db8de5c","hash":"750d3c182547aad3a75b74326db8de5c","service":"texture2dService"}},"8f01e5R-9af7bcE-e63d91S-42e127R":{"path":"8f/8f01e5R-9af7bcE-e63d91S-42e127R.platform","tempPath":"","meta":{"uuid":"8f01e5R-9af7bcE-e63d91S-42e127R","importSettings":{"textureData":{"data":{"width":400,"height":400,"sRGB":true,"needPremultiplyAlpha":false,"useMipmap":false,"mipmap":1,"wrapU":2,"wrapV":2,"filterMode":0,"pixelFormat":2,"anisoLevel":1,"wrapS":2,"wrapT":2},"editorInfo":{"assetVersion":2,"enableCompress":true}},"__localId":{"texture2d":1},"metaMTime":1604661026096,"inheritGroupId":true,"groupId":"","isEntries":"false","recursiveSetEntries":true,"isPackInBuildIn":"false"},"ver":"1","dependencies":["a5d758R-1c18d1E-050173S-f6814bR","737658R-ecb5abE-51329dS-c68b24R","d5886fR-d657c7E-0927f6S-a9acc4R"],"fileDependencies":[],"size":127,"srcHash":"e3874e50b2060661749ba221bbc32822","hash":"e3874e50b2060661749ba221bbc32822","service":"texture2dService"}},"737658R-ecb5abE-51329dS-c68b24R":{"path":"73/737658R-ecb5abE-51329dS-c68b24R.texture2d","tempPath":"","meta":{"uuid":"737658R-ecb5abE-51329dS-c68b24R","importSettings":{},"ver":"1","dependencies":[],"fileDependencies":["d35a5aF-aebf33I-f77397L-8ab293E"],"size":241,"hash":"ac7214dae6446a768a1e58cb4f8159e8","srcHash":"ac7214dae6446a768a1e58cb4f8159e8","service":"texture2dService"}},"d35a5aF-aebf33I-f77397L-8ab293E":{"path":"d3/d35a5aF-aebf33I-f77397L-8ab293E.etc2.ktx","tempPath":"","meta":{"uuid":"d35a5aF-aebf33I-f77397L-8ab293E","importSettings":{"relatedSrcUuid":"4496a9F-f5e408I-368031L-edae2eE"},"ver":"1","dependencies":[],"fileDependencies":[],"size":160100,"srcHash":"929afd64b7f955f8289305a073af43d9","hash":"929afd64b7f955f8289305a073af43d9","service":"texture2dService"}},"d5886fR-d657c7E-0927f6S-a9acc4R":{"path":"d5/d5886fR-d657c7E-0927f6S-a9acc4R.texture2d","tempPath":"","meta":{"uuid":"d5886fR-d657c7E-0927f6S-a9acc4R","importSettings":{},"ver":"1","dependencies":[],"fileDependencies":["b9611aF-591ff2I-f20798L-07cf69E"],"size":241,"hash":"3139e70a4f9e4c1bc85068e4312c615b","srcHash":"3139e70a4f9e4c1bc85068e4312c615b","service":"texture2dService"}},"b9611aF-591ff2I-f20798L-07cf69E":{"path":"b9/b9611aF-591ff2I-f20798L-07cf69E.astc.ktx","tempPath":"","meta":{"uuid":"b9611aF-591ff2I-f20798L-07cf69E","importSettings":{"relatedSrcUuid":"4496a9F-f5e408I-368031L-edae2eE"},"ver":"1","dependencies":[],"fileDependencies":[],"size":40100,"srcHash":"f8aec1cf3917ca41540da719dea849f6","hash":"f8aec1cf3917ca41540da719dea849f6","service":"texture2dService"}},"9d6ea7R-86fc6fE-1102a6S-fa9bb1R":{"path":"9d/9d6ea7R-86fc6fE-1102a6S-fa9bb1R.platform","tempPath":"","meta":{"uuid":"9d6ea7R-86fc6fE-1102a6S-fa9bb1R","importSettings":{"textureData":{"data":{"width":512,"height":512,"sRGB":true,"needPremultiplyAlpha":false,"useMipmap":true,"mipmap":10,"wrapU":1,"wrapV":1,"filterMode":2,"pixelFormat":2,"anisoLevel":1},"editorInfo":{"assetVersion":2,"enableCompress":true}},"__localId":{"texture2d":1},"metaMTime":1604661026008,"inheritGroupId":true,"groupId":"","isEntries":"false","recursiveSetEntries":true,"isPackInBuildIn":"false"},"ver":"1","dependencies":["1fe445R-5afe4eE-682922S-fe7185R","c88796R-87e3ccE-d89253S-4497ccR","3680a4R-c721feE-a27334S-37eab0R","3cf718R-22ed3bE-8fee1bS-78653bR","000f1fR-a27bc5E-a51f8aS-3b9a0aR"],"fileDependencies":[],"size":208,"srcHash":"4a0ade590c91f264f49d3848433cc91d","hash":"4a0ade590c91f264f49d3848433cc91d","service":"texture2dService"}},"c88796R-87e3ccE-d89253S-4497ccR":{"path":"c8/c88796R-87e3ccE-d89253S-4497ccR.texture2d","tempPath":"","meta":{"uuid":"c88796R-87e3ccE-d89253S-4497ccR","importSettings":{},"ver":"1","dependencies":[],"fileDependencies":["8f01b8F-01d00dI-f53997L-be6bc8E"],"size":221,"hash":"4058cbb3fda4e5b667b715c9527882ae","srcHash":"4058cbb3fda4e5b667b715c9527882ae","service":"texture2dService"}},"8f01b8F-01d00dI-f53997L-be6bc8E":{"path":"8f/8f01b8F-01d00dI-f53997L-be6bc8E.etc2.ktx","tempPath":"","meta":{"uuid":"8f01b8F-01d00dI-f53997L-be6bc8E","importSettings":{"relatedSrcUuid":"e243c4F-e773dfI-1f03ccL-ef8048E"},"ver":"1","dependencies":[],"fileDependencies":[],"size":174912,"srcHash":"f977d4d703e8cec7c71147ea55c1486c","hash":"f977d4d703e8cec7c71147ea55c1486c","service":"texture2dService"}},"3680a4R-c721feE-a27334S-37eab0R":{"path":"36/3680a4R-c721feE-a27334S-37eab0R.texture2d","tempPath":"","meta":{"uuid":"3680a4R-c721feE-a27334S-37eab0R","importSettings":{},"ver":"1","dependencies":[],"fileDependencies":["983236F-9e397aI-bd4c25L-bea1ebE"],"size":221,"hash":"517595879ce2a5f0e457713481b63f14","srcHash":"517595879ce2a5f0e457713481b63f14","service":"texture2dService"}},"983236F-9e397aI-bd4c25L-bea1ebE":{"path":"98/983236F-9e397aI-bd4c25L-bea1ebE.astc.ktx","tempPath":"","meta":{"uuid":"983236F-9e397aI-bd4c25L-bea1ebE","importSettings":{"relatedSrcUuid":"e243c4F-e773dfI-1f03ccL-ef8048E"},"ver":"1","dependencies":[],"fileDependencies":[],"size":87560,"srcHash":"df21da447f459108cfd39ff48478490d","hash":"df21da447f459108cfd39ff48478490d","service":"texture2dService"}},"3cf718R-22ed3bE-8fee1bS-78653bR":{"path":"3c/3cf718R-22ed3bE-8fee1bS-78653bR.texture2d","tempPath":"","meta":{"uuid":"3cf718R-22ed3bE-8fee1bS-78653bR","importSettings":{},"ver":"1","dependencies":[],"fileDependencies":["8fe792F-f056caI-a2e1a9L-63ae58E"],"size":221,"hash":"502d11ba68108b811a521f3739bb639f","srcHash":"502d11ba68108b811a521f3739bb639f","service":"texture2dService"}},"8fe792F-f056caI-a2e1a9L-63ae58E":{"path":"8f/8fe792F-f056caI-a2e1a9L-63ae58E.pvr.pvr","tempPath":"","meta":{"uuid":"8fe792F-f056caI-a2e1a9L-63ae58E","importSettings":{"relatedSrcUuid":"e243c4F-e773dfI-1f03ccL-ef8048E"},"ver":"1","dependencies":[],"fileDependencies":[],"size":174915,"srcHash":"a0112a1c9001fcd7ceec9c83ea7fcf93","hash":"a0112a1c9001fcd7ceec9c83ea7fcf93","service":"texture2dService"}},"000f1fR-a27bc5E-a51f8aS-3b9a0aR":{"path":"00/000f1fR-a27bc5E-a51f8aS-3b9a0aR.texture2d","tempPath":"","meta":{"uuid":"000f1fR-a27bc5E-a51f8aS-3b9a0aR","importSettings":{},"ver":"1","dependencies":[],"fileDependencies":["789e47F-5c1860I-466b54L-79558aE"],"size":221,"hash":"81eab02e37a898013972de627faf90cf","srcHash":"81eab02e37a898013972de627faf90cf","service":"texture2dService"}},"789e47F-5c1860I-466b54L-79558aE":{"path":"78/789e47F-5c1860I-466b54L-79558aE.etc1.ktx","tempPath":"","meta":{"uuid":"789e47F-5c1860I-466b54L-79558aE","importSettings":{"relatedSrcUuid":"e243c4F-e773dfI-1f03ccL-ef8048E"},"ver":"1","dependencies":[],"fileDependencies":[],"size":174912,"srcHash":"058a506f883aec20c8f2cc853d2510d2","hash":"058a506f883aec20c8f2cc853d2510d2","service":"texture2dService"}},"be1ec9R-485a70E-77aaf6S-f56022R":{"path":"be/be1ec9R-485a70E-77aaf6S-f56022R.platform","tempPath":"","meta":{"uuid":"be1ec9R-485a70E-77aaf6S-f56022R","importSettings":{"textureData":{"data":{"width":256,"height":256,"sRGB":true,"needPremultiplyAlpha":false,"useMipmap":false,"mipmap":1,"wrapU":2,"wrapV":2,"filterMode":1,"pixelFormat":2,"anisoLevel":1},"editorInfo":{"assetVersion":2,"enableCompress":true}},"__localId":{"texture2d":1},"metaMTime":1604661025967,"inheritGroupId":true,"groupId":"","isEntries":"false","recursiveSetEntries":true,"isPackInBuildIn":"false"},"ver":"1","dependencies":["7479ffR-73c9baE-02cb32S-8ec50fR","3d7b82R-116d9cE-675d66S-16a3faR","fa04f6R-3c5b06E-4318b3S-ebe46bR","4e83ddR-422124E-16d95eS-4ca7b6R"],"fileDependencies":[],"size":167,"srcHash":"4cdf86c7723797f12dd77643a7c53f25","hash":"4cdf86c7723797f12dd77643a7c53f25","service":"texture2dService"}},"3d7b82R-116d9cE-675d66S-16a3faR":{"path":"3d/3d7b82R-116d9cE-675d66S-16a3faR.texture2d","tempPath":"","meta":{"uuid":"3d7b82R-116d9cE-675d66S-16a3faR","importSettings":{},"ver":"1","dependencies":[],"fileDependencies":["c7aba5F-1aee3fI-48742dL-d9fa17E"],"size":221,"hash":"d4a936db655c2af4323725263203acee","srcHash":"d4a936db655c2af4323725263203acee","service":"texture2dService"}},"c7aba5F-1aee3fI-48742dL-d9fa17E":{"path":"c7/c7aba5F-1aee3fI-48742dL-d9fa17E.etc2.ktx","tempPath":"","meta":{"uuid":"c7aba5F-1aee3fI-48742dL-d9fa17E","importSettings":{"relatedSrcUuid":"18c880F-79fd53I-da12d9L-0be16fE"},"ver":"1","dependencies":[],"fileDependencies":[],"size":65636,"srcHash":"ea983adbaa6c7da3b526a2a605e3dca7","hash":"ea983adbaa6c7da3b526a2a605e3dca7","service":"texture2dService"}},"fa04f6R-3c5b06E-4318b3S-ebe46bR":{"path":"fa/fa04f6R-3c5b06E-4318b3S-ebe46bR.texture2d","tempPath":"","meta":{"uuid":"fa04f6R-3c5b06E-4318b3S-ebe46bR","importSettings":{},"ver":"1","dependencies":[],"fileDependencies":["71c119F-4cc5cdI-8bff77L-170967E"],"size":221,"hash":"f077c416a52c66b2a41a139853d3043d","srcHash":"f077c416a52c66b2a41a139853d3043d","service":"texture2dService"}},"71c119F-4cc5cdI-8bff77L-170967E":{"path":"71/71c119F-4cc5cdI-8bff77L-170967E.astc.ktx","tempPath":"","meta":{"uuid":"71c119F-4cc5cdI-8bff77L-170967E","importSettings":{"relatedSrcUuid":"18c880F-79fd53I-da12d9L-0be16fE"},"ver":"1","dependencies":[],"fileDependencies":[],"size":16484,"srcHash":"bf2c0562508f92fc5a7a42b5e3dba5ff","hash":"bf2c0562508f92fc5a7a42b5e3dba5ff","service":"texture2dService"}},"4e83ddR-422124E-16d95eS-4ca7b6R":{"path":"4e/4e83ddR-422124E-16d95eS-4ca7b6R.texture2d","tempPath":"","meta":{"uuid":"4e83ddR-422124E-16d95eS-4ca7b6R","importSettings":{},"ver":"1","dependencies":[],"fileDependencies":["7b14beF-3ddf34I-69b8dcL-b7be53E"],"size":221,"hash":"99a2fca54288069b2ce3978ae2882279","srcHash":"99a2fca54288069b2ce3978ae2882279","service":"texture2dService"}},"7b14beF-3ddf34I-69b8dcL-b7be53E":{"path":"7b/7b14beF-3ddf34I-69b8dcL-b7be53E.pvr.pvr","tempPath":"","meta":{"uuid":"7b14beF-3ddf34I-69b8dcL-b7be53E","importSettings":{"relatedSrcUuid":"18c880F-79fd53I-da12d9L-0be16fE"},"ver":"1","dependencies":[],"fileDependencies":[],"size":32835,"srcHash":"b659ed2179ba6fab5384c50b4a8720d8","hash":"b659ed2179ba6fab5384c50b4a8720d8","service":"texture2dService"}},"d599e1R-1b7d8bE-cd434fS-9ec036R":{"path":"d5/d599e1R-1b7d8bE-cd434fS-9ec036R.platform","tempPath":"","meta":{"uuid":"d599e1R-1b7d8bE-cd434fS-9ec036R","importSettings":{"textureData":{"data":{"width":128,"height":128,"sRGB":true,"needPremultiplyAlpha":false,"useMipmap":true,"mipmap":8,"wrapU":1,"wrapV":1,"filterMode":2,"pixelFormat":2,"anisoLevel":1},"editorInfo":{"assetVersion":2,"enableCompress":true}},"__localId":{"texture2d":1},"metaMTime":1604661025944,"inheritGroupId":true,"groupId":"","isEntries":"false","recursiveSetEntries":true,"isPackInBuildIn":"false"},"ver":"1","dependencies":["b0d843R-2c7dbeE-16080dS-63ada6R","23fde3R-7daa91E-1451a0S-711008R","ed3317R-6951bbE-a4aa5aS-c3810cR","4d500fR-8e738cE-9aaa4cS-85afa7R"],"fileDependencies":[],"size":167,"srcHash":"69159555e6c2dffe05abc3233d91d193","hash":"69159555e6c2dffe05abc3233d91d193","service":"texture2dService"}},"23fde3R-7daa91E-1451a0S-711008R":{"path":"23/23fde3R-7daa91E-1451a0S-711008R.texture2d","tempPath":"","meta":{"uuid":"23fde3R-7daa91E-1451a0S-711008R","importSettings":{},"ver":"1","dependencies":[],"fileDependencies":["c3912dF-88dce0I-3ffe30L-42c349E"],"size":220,"hash":"5864d1d5de4dc7e34fa96f8c3b727452","srcHash":"5864d1d5de4dc7e34fa96f8c3b727452","service":"texture2dService"}},"c3912dF-88dce0I-3ffe30L-42c349E":{"path":"c3/c3912dF-88dce0I-3ffe30L-42c349E.etc2.ktx","tempPath":"","meta":{"uuid":"c3912dF-88dce0I-3ffe30L-42c349E","importSettings":{"relatedSrcUuid":"5a7b80F-d1c0a9I-7018cbL-2b13a5E"},"ver":"1","dependencies":[],"fileDependencies":[],"size":22000,"srcHash":"814eab145ead9428d66fba88fb2c8abd","hash":"814eab145ead9428d66fba88fb2c8abd","service":"texture2dService"}},"ed3317R-6951bbE-a4aa5aS-c3810cR":{"path":"ed/ed3317R-6951bbE-a4aa5aS-c3810cR.texture2d","tempPath":"","meta":{"uuid":"ed3317R-6951bbE-a4aa5aS-c3810cR","importSettings":{},"ver":"1","dependencies":[],"fileDependencies":["bdb685F-603eaaI-0e3f5eL-9a6970E"],"size":220,"hash":"c01d096b0ff9df424986b0cd2655e344","srcHash":"c01d096b0ff9df424986b0cd2655e344","service":"texture2dService"}},"bdb685F-603eaaI-0e3f5eL-9a6970E":{"path":"bd/bdb685F-603eaaI-0e3f5eL-9a6970E.astc.ktx","tempPath":"","meta":{"uuid":"bdb685F-603eaaI-0e3f5eL-9a6970E","importSettings":{"relatedSrcUuid":"5a7b80F-d1c0a9I-7018cbL-2b13a5E"},"ver":"1","dependencies":[],"fileDependencies":[],"size":5632,"srcHash":"5be699203cdc5570454fba006cb4c447","hash":"5be699203cdc5570454fba006cb4c447","service":"texture2dService"}},"4d500fR-8e738cE-9aaa4cS-85afa7R":{"path":"4d/4d500fR-8e738cE-9aaa4cS-85afa7R.texture2d","tempPath":"","meta":{"uuid":"4d500fR-8e738cE-9aaa4cS-85afa7R","importSettings":{},"ver":"1","dependencies":[],"fileDependencies":["8cb7dfF-c351fbI-5f6c9cL-2eee4dE"],"size":220,"hash":"57d0392d3b211e982e304dbcecdace0d","srcHash":"57d0392d3b211e982e304dbcecdace0d","service":"texture2dService"}},"8cb7dfF-c351fbI-5f6c9cL-2eee4dE":{"path":"8c/8cb7dfF-c351fbI-5f6c9cL-2eee4dE.pvr.pvr","tempPath":"","meta":{"uuid":"8cb7dfF-c351fbI-5f6c9cL-2eee4dE","importSettings":{"relatedSrcUuid":"5a7b80F-d1c0a9I-7018cbL-2b13a5E"},"ver":"1","dependencies":[],"fileDependencies":[],"size":11075,"srcHash":"d528528981e0b42dff0d3352e1242ec3","hash":"d528528981e0b42dff0d3352e1242ec3","service":"texture2dService"}},"e1cc29R-ba94e7E-111661S-d09925R":{"path":"e1/e1cc29R-ba94e7E-111661S-d09925R.platform","tempPath":"","meta":{"uuid":"e1cc29R-ba94e7E-111661S-d09925R","importSettings":{"textureData":{"data":{"width":128,"height":128,"sRGB":true,"needPremultiplyAlpha":false,"useMipmap":true,"mipmap":8,"wrapU":1,"wrapV":1,"filterMode":2,"pixelFormat":2,"anisoLevel":1},"editorInfo":{"assetVersion":2,"enableCompress":true}},"__localId":{"texture2d":1},"metaMTime":1604661025934,"inheritGroupId":true,"groupId":"","isEntries":"false","recursiveSetEntries":true,"isPackInBuildIn":"false"},"ver":"1","dependencies":["a3b552R-3ab22fE-1af925S-17deb8R","6b5ef8R-eeac19E-50ee57S-61f413R","70345bR-2e00bcE-9e34f3S-bf0594R","6c94b8R-1891a2E-e0d10fS-eb2386R"],"fileDependencies":[],"size":167,"srcHash":"b9253fe3fb137035df2a7a155d97405c","hash":"b9253fe3fb137035df2a7a155d97405c","service":"texture2dService"}},"6b5ef8R-eeac19E-50ee57S-61f413R":{"path":"6b/6b5ef8R-eeac19E-50ee57S-61f413R.texture2d","tempPath":"","meta":{"uuid":"6b5ef8R-eeac19E-50ee57S-61f413R","importSettings":{},"ver":"1","dependencies":[],"fileDependencies":["74b408F-4550e4I-849bfbL-7d5ab9E"],"size":220,"hash":"45618b91c67273daa9d29cb9b0be78a8","srcHash":"45618b91c67273daa9d29cb9b0be78a8","service":"texture2dService"}},"74b408F-4550e4I-849bfbL-7d5ab9E":{"path":"74/74b408F-4550e4I-849bfbL-7d5ab9E.etc2.ktx","tempPath":"","meta":{"uuid":"74b408F-4550e4I-849bfbL-7d5ab9E","importSettings":{"relatedSrcUuid":"a9dadbF-357f88I-e647caL-128c85E"},"ver":"1","dependencies":[],"fileDependencies":[],"size":22000,"srcHash":"ffdc975271f49a988057d9f4d7faa407","hash":"ffdc975271f49a988057d9f4d7faa407","service":"texture2dService"}},"70345bR-2e00bcE-9e34f3S-bf0594R":{"path":"70/70345bR-2e00bcE-9e34f3S-bf0594R.texture2d","tempPath":"","meta":{"uuid":"70345bR-2e00bcE-9e34f3S-bf0594R","importSettings":{},"ver":"1","dependencies":[],"fileDependencies":["c79e37F-b1c031I-3d2bc2L-3899c3E"],"size":220,"hash":"1a7fb846954753632b10e0d84c47aedc","srcHash":"1a7fb846954753632b10e0d84c47aedc","service":"texture2dService"}},"c79e37F-b1c031I-3d2bc2L-3899c3E":{"path":"c7/c79e37F-b1c031I-3d2bc2L-3899c3E.astc.ktx","tempPath":"","meta":{"uuid":"c79e37F-b1c031I-3d2bc2L-3899c3E","importSettings":{"relatedSrcUuid":"a9dadbF-357f88I-e647caL-128c85E"},"ver":"1","dependencies":[],"fileDependencies":[],"size":5632,"srcHash":"af67dfa0c1192bf99bf5207dc2033bd1","hash":"af67dfa0c1192bf99bf5207dc2033bd1","service":"texture2dService"}},"6c94b8R-1891a2E-e0d10fS-eb2386R":{"path":"6c/6c94b8R-1891a2E-e0d10fS-eb2386R.texture2d","tempPath":"","meta":{"uuid":"6c94b8R-1891a2E-e0d10fS-eb2386R","importSettings":{},"ver":"1","dependencies":[],"fileDependencies":["e7d1b7F-2efa42I-5f0797L-067c4cE"],"size":220,"hash":"06eb7fc4d9bb1c4a174eb39f7afb1a99","srcHash":"06eb7fc4d9bb1c4a174eb39f7afb1a99","service":"texture2dService"}},"e7d1b7F-2efa42I-5f0797L-067c4cE":{"path":"e7/e7d1b7F-2efa42I-5f0797L-067c4cE.pvr.pvr","tempPath":"","meta":{"uuid":"e7d1b7F-2efa42I-5f0797L-067c4cE","importSettings":{"relatedSrcUuid":"a9dadbF-357f88I-e647caL-128c85E"},"ver":"1","dependencies":[],"fileDependencies":[],"size":11075,"srcHash":"d36bccb381b97035c1837d5791ad8cd6","hash":"d36bccb381b97035c1837d5791ad8cd6","service":"texture2dService"}},"eb5df0R-ec8261E-ec8a94S-2dfd26R":{"path":"eb/eb5df0R-ec8261E-ec8a94S-2dfd26R.platform","tempPath":"","meta":{"uuid":"eb5df0R-ec8261E-ec8a94S-2dfd26R","importSettings":{"textureData":{"data":{"width":26,"height":37,"sRGB":true,"needPremultiplyAlpha":false,"useMipmap":false,"mipmap":1,"wrapU":2,"wrapV":2,"filterMode":0,"pixelFormat":2,"anisoLevel":1},"editorInfo":{"assetVersion":2,"enableCompress":true}},"__localId":{"texture2d":1},"metaMTime":1604661026035,"inheritGroupId":true,"groupId":"","isEntries":"false","recursiveSetEntries":true,"isPackInBuildIn":"false"},"ver":"1","dependencies":["894015R-3f2fd8E-9fcebcS-6a181fR","6fea46R-40a5f2E-50e0c2S-ba7aebR","ff99afR-0fce38E-5c156fS-e77243R"],"fileDependencies":[],"size":127,"srcHash":"69c454e3adeacd6fab9268ee45b8c639","hash":"69c454e3adeacd6fab9268ee45b8c639","service":"texture2dService"}},"6fea46R-40a5f2E-50e0c2S-ba7aebR":{"path":"6f/6fea46R-40a5f2E-50e0c2S-ba7aebR.texture2d","tempPath":"","meta":{"uuid":"6fea46R-40a5f2E-50e0c2S-ba7aebR","importSettings":{},"ver":"1","dependencies":[],"fileDependencies":["75a201F-6904e5I-9ab6cdL-cfe228E"],"size":219,"hash":"9ce3606189bd7af4ff0423341fbda90b","srcHash":"9ce3606189bd7af4ff0423341fbda90b","service":"texture2dService"}},"75a201F-6904e5I-9ab6cdL-cfe228E":{"path":"75/75a201F-6904e5I-9ab6cdL-cfe228E.etc2.ktx","tempPath":"","meta":{"uuid":"75a201F-6904e5I-9ab6cdL-cfe228E","importSettings":{"relatedSrcUuid":"0afeedF-26b84aI-dfda01L-b682c6E"},"ver":"1","dependencies":[],"fileDependencies":[],"size":1220,"srcHash":"d5940dd59f5d1f21874886c301d0918b","hash":"d5940dd59f5d1f21874886c301d0918b","service":"texture2dService"}},"ff99afR-0fce38E-5c156fS-e77243R":{"path":"ff/ff99afR-0fce38E-5c156fS-e77243R.texture2d","tempPath":"","meta":{"uuid":"ff99afR-0fce38E-5c156fS-e77243R","importSettings":{},"ver":"1","dependencies":[],"fileDependencies":["d1766aF-d585bbI-f3b8e1L-3846acE"],"size":219,"hash":"c8fae2352bb72b06d0e8ebc8539f18b6","srcHash":"c8fae2352bb72b06d0e8ebc8539f18b6","service":"texture2dService"}},"d1766aF-d585bbI-f3b8e1L-3846acE":{"path":"d1/d1766aF-d585bbI-f3b8e1L-3846acE.astc.ktx","tempPath":"","meta":{"uuid":"d1766aF-d585bbI-f3b8e1L-3846acE","importSettings":{"relatedSrcUuid":"0afeedF-26b84aI-dfda01L-b682c6E"},"ver":"1","dependencies":[],"fileDependencies":[],"size":420,"srcHash":"6d94c27bb783b8adf5d29ea6945d4687","hash":"6d94c27bb783b8adf5d29ea6945d4687","service":"texture2dService"}},"0f3a56R-59ed39E-b1d9bdS-cdafa4R":{"path":"script/Scripts/components/d3Main.js","tempPath":"","meta":{"uuid":"0f3a56R-59ed39E-b1d9bdS-cdafa4R","importSettings":{"inheritGroupId":true,"groupId":"","isEntries":"false","recursiveSetEntries":true,"isPackInBuildIn":"false"},"ver":"1","dependencies":[],"fileDependencies":[],"size":1989,"srcHash":"5858d9c23a3cc1a3246d8c93a50d605a","hash":"5858d9c23a3cc1a3246d8c93a50d605a","service":"heavyTypescriptService"}},"1c651dR-7719a6E-f316e9S-ea26eeR":{"path":"script/Scripts/bunnyTest.js","tempPath":"","meta":{"uuid":"1c651dR-7719a6E-f316e9S-ea26eeR","importSettings":{"inheritGroupId":true,"groupId":"","isEntries":"false","recursiveSetEntries":true,"isPackInBuildIn":"false"},"ver":"1","size":3159,"srcHash":"3b2635fcde0708376a1eb5f255596742","hash":"3b2635fcde0708376a1eb5f255596742","service":"heavyTypescriptService","dependencies":[],"fileDependencies":[]}},"301290R-667988E-d7739dS-7af69bR":{"path":"script/Scripts/components/d3Enemy.js","tempPath":"","meta":{"uuid":"301290R-667988E-d7739dS-7af69bR","importSettings":{"inheritGroupId":true,"groupId":"","isEntries":"false","recursiveSetEntries":true,"isPackInBuildIn":"false"},"ver":"1","dependencies":[],"fileDependencies":[],"size":2535,"srcHash":"77dd6c14a532d2392d0f0318aec77763","hash":"77dd6c14a532d2392d0f0318aec77763","service":"heavyTypescriptService"}},"4067f0R-39bb01E-e28ce3S-842a98R":{"path":"script/Scripts/components/d2Shoot.js","tempPath":"","meta":{"uuid":"4067f0R-39bb01E-e28ce3S-842a98R","importSettings":{"inheritGroupId":true,"groupId":"","isEntries":"false","recursiveSetEntries":true,"isPackInBuildIn":"false"},"ver":"1","dependencies":[],"fileDependencies":[],"size":907,"srcHash":"a68406e3aa39c6f260096b2f07d6f42a","hash":"a68406e3aa39c6f260096b2f07d6f42a","service":"heavyTypescriptService"}},"4f1ca0R-6b9050E-fce1ddS-e62c00R":{"path":"script/Scripts/components/d3Player.js","tempPath":"","meta":{"uuid":"4f1ca0R-6b9050E-fce1ddS-e62c00R","importSettings":{"inheritGroupId":true,"groupId":"","isEntries":"false","recursiveSetEntries":true,"isPackInBuildIn":"false"},"ver":"1","dependencies":[],"fileDependencies":[],"size":3802,"srcHash":"d6b1c1e58491296d2922f38c7c7f32f5","hash":"d6b1c1e58491296d2922f38c7c7f32f5","service":"heavyTypescriptService"}},"7504d5R-0bd646E-3ac404S-865d15R":{"path":"script/Scripts/components/d3Camera.js","tempPath":"","meta":{"uuid":"7504d5R-0bd646E-3ac404S-865d15R","importSettings":{"inheritGroupId":true,"groupId":"","isEntries":"false","recursiveSetEntries":true,"isPackInBuildIn":"false"},"ver":"1","dependencies":[],"fileDependencies":[],"size":1090,"srcHash":"7cef02d58d7d8cda205618c3a4edf095","hash":"7cef02d58d7d8cda205618c3a4edf095","service":"heavyTypescriptService"}},"784034R-d88486E-6e9449S-26f3b3R":{"path":"script/Scripts/commons/dataCenter.js","tempPath":"","meta":{"uuid":"784034R-d88486E-6e9449S-26f3b3R","importSettings":{"inheritGroupId":true,"groupId":"","isEntries":"false","recursiveSetEntries":true,"isPackInBuildIn":"false"},"ver":"1","dependencies":[],"fileDependencies":[],"size":180,"srcHash":"3bdec861777342b25cebe9b95925a347","hash":"3bdec861777342b25cebe9b95925a347","service":"heavyTypescriptService"}},"810cc3R-d8c1feE-b1d05fS-a52355R":{"path":"script/Scripts/commons/eventCenter.js","tempPath":"","meta":{"uuid":"810cc3R-d8c1feE-b1d05fS-a52355R","importSettings":{"inheritGroupId":true,"groupId":"","isEntries":"false","recursiveSetEntries":true,"isPackInBuildIn":"false"},"ver":"1","dependencies":[],"fileDependencies":[],"size":456,"srcHash":"71331a914c0a30aed57e703b62093c61","hash":"71331a914c0a30aed57e703b62093c61","service":"heavyTypescriptService"}},"929ff6R-cb6573E-6e4cf4S-4fe0a9R":{"path":"script/Scripts/components/d3Bullet.js","tempPath":"","meta":{"uuid":"929ff6R-cb6573E-6e4cf4S-4fe0a9R","importSettings":{"inheritGroupId":true,"groupId":"","isEntries":"false","recursiveSetEntries":true,"isPackInBuildIn":"false"},"ver":"1","dependencies":[],"fileDependencies":[],"size":1091,"srcHash":"a7649a5646ec80cc395f2edc0a884558","hash":"a7649a5646ec80cc395f2edc0a884558","service":"heavyTypescriptService"}},"b196f7R-769516E-e4b208S-3ff571R":{"path":"script/Scripts/components/d2Move.js","tempPath":"","meta":{"uuid":"b196f7R-769516E-e4b208S-3ff571R","importSettings":{"inheritGroupId":true,"groupId":"","isEntries":"false","recursiveSetEntries":true,"isPackInBuildIn":"false"},"ver":"1","dependencies":[],"fileDependencies":[],"size":2487,"srcHash":"9fd1eb0a1db4059e7396b4d6b01acd07","hash":"9fd1eb0a1db4059e7396b4d6b01acd07","service":"heavyTypescriptService"}},"bd54dcR-0b4fc7E-6416f5S-3e7770R":{"path":"script/Scripts/components/d2Score.js","tempPath":"","meta":{"uuid":"bd54dcR-0b4fc7E-6416f5S-3e7770R","importSettings":{"inheritGroupId":true,"groupId":"","isEntries":"false","recursiveSetEntries":true,"isPackInBuildIn":"false"},"ver":"1","dependencies":[],"fileDependencies":[],"size":604,"srcHash":"0381bf3effa8e50faaec4f8a6e0d7854","hash":"0381bf3effa8e50faaec4f8a6e0d7854","service":"heavyTypescriptService"}},"fc827dR-2675d1E-e9edf0S-9750eeR":{"path":"script/Scripts/commons/collider.js","tempPath":"","meta":{"uuid":"fc827dR-2675d1E-e9edf0S-9750eeR","importSettings":{"inheritGroupId":true,"groupId":"","isEntries":"false","recursiveSetEntries":true,"isPackInBuildIn":"false"},"ver":"1","dependencies":[],"fileDependencies":[],"size":3001,"srcHash":"24f634060ec41d0e9b3103e5d0b9fb4e","hash":"24f634060ec41d0e9b3103e5d0b9fb4e","service":"heavyTypescriptService"}},"062660F-f34be3I-ab1986L-df827cE":{"path":"06/062660F-f34be3I-ab1986L-df827cE.bin","tempPath":"","meta":{"uuid":"062660F-f34be3I-ab1986L-df827cE","importSettings":{"relatedSrcUuid":"9b0f03R-85c949E-1f86daS-4dccd9R"},"ver":"1","dependencies":[],"fileDependencies":[],"size":1036,"hash":"a14167e4bae45b1043d3378d57210fe2","srcHash":"a14167e4bae45b1043d3378d57210fe2","service":"defaultService"}},"0708fcR-f9d3a0E-d860ceS-176f68R":{"path":"07/0708fcR-f9d3a0E-d860ceS-176f68R.spriteframe","tempPath":"","meta":{"uuid":"0708fcR-f9d3a0E-d860ceS-176f68R","importSettings":{"inheritGroupId":true,"groupId":"","isEntries":"false","recursiveSetEntries":true,"isPackInBuildIn":"false"},"ver":"1","dependencies":["4a50ccR-e2e892E-7347deS-4483d1R"],"fileDependencies":[],"size":66,"service":"defaultService","hash":"fd0ecd743cee46de2e0f62d8c310472b","srcHash":"fd0ecd743cee46de2e0f62d8c310472b"}},"0863a5R-27792bE-e2082bS-5a9b9bR":{"path":"08/0863a5R-27792bE-e2082bS-5a9b9bR.mat","tempPath":"","meta":{"uuid":"0863a5R-27792bE-e2082bS-5a9b9bR","importSettings":{"inheritGroupId":true,"groupId":"","isEntries":"false","recursiveSetEntries":true,"isPackInBuildIn":"false"},"ver":"1","size":427,"service":"defaultService","hash":"2001302cf05a562e0c143fb5c1de3638","dependencies":["1aa5b1R-f50db4E-88d79fS-cf7426R","c7fb21R-abb109E-a8e91bS-54b4baR"],"fileDependencies":[],"srcHash":"2001302cf05a562e0c143fb5c1de3638"}},"0a74a6F-e91e17I-33a59bL-16e923E":{"path":"0a/0a74a6F-e91e17I-33a59bL-16e923E.png","tempPath":"","meta":{"uuid":"0a74a6F-e91e17I-33a59bL-16e923E","hash":"b1d65efce69a9e2e28bdfd263152a2eb","srcHash":"b1d65efce69a9e2e28bdfd263152a2eb","importSettings":{"textureData":{"data":{"width":128,"height":128,"sRGB":true,"needPremultiplyAlpha":false,"useMipmap":true,"mipmap":8,"wrapU":1,"wrapV":1,"filterMode":2,"pixelFormat":2,"anisoLevel":1},"editorInfo":{"assetVersion":2,"enableCompress":true}},"__localId":{"texture2d":1},"metaMTime":1604661025975,"inheritGroupId":true,"groupId":"","isEntries":"false","recursiveSetEntries":true,"isPackInBuildIn":"false"},"dependencies":[],"fileDependencies":[],"size":13502,"service":"defaultService"}},"0afeedF-26b84aI-dfda01L-b682c6E":{"path":"0a/0afeedF-26b84aI-dfda01L-b682c6E.png","tempPath":"","meta":{"uuid":"0afeedF-26b84aI-dfda01L-b682c6E","hash":"1e41031211851366f68597ab2fa073f2","srcHash":"1e41031211851366f68597ab2fa073f2","importSettings":{"textureData":{"data":{"width":26,"height":37,"sRGB":true,"needPremultiplyAlpha":false,"useMipmap":false,"mipmap":1,"wrapU":2,"wrapV":2,"filterMode":0,"pixelFormat":2,"anisoLevel":1},"editorInfo":{"assetVersion":2,"enableCompress":true}},"__localId":{"texture2d":1},"metaMTime":1604661026035,"inheritGroupId":true,"groupId":"","isEntries":"false","recursiveSetEntries":true,"isPackInBuildIn":"false"},"dependencies":[],"fileDependencies":[],"size":2050,"service":"defaultService"}},"18c880F-79fd53I-da12d9L-0be16fE":{"path":"18/18c880F-79fd53I-da12d9L-0be16fE.png","tempPath":"","meta":{"uuid":"18c880F-79fd53I-da12d9L-0be16fE","hash":"e57ce499a96f45618158704759677094","srcHash":"e57ce499a96f45618158704759677094","importSettings":{"textureData":{"data":{"width":256,"height":256,"sRGB":true,"needPremultiplyAlpha":false,"useMipmap":false,"mipmap":1,"wrapU":2,"wrapV":2,"filterMode":1,"pixelFormat":2,"anisoLevel":1},"editorInfo":{"assetVersion":2,"enableCompress":true}},"__localId":{"texture2d":1},"metaMTime":1604661025967,"inheritGroupId":true,"groupId":"","isEntries":"false","recursiveSetEntries":true,"isPackInBuildIn":"false"},"dependencies":[],"fileDependencies":[],"size":110086,"service":"defaultService"}},"18dcebF-c71d74I-c1de04L-03fa2eE":{"path":"18/18dcebF-c71d74I-c1de04L-03fa2eE.bin","tempPath":"","meta":{"uuid":"18dcebF-c71d74I-c1de04L-03fa2eE","importSettings":{"relatedSrcUuid":"54c366R-18c89dE-201764S-f4ffb9R"},"ver":"1","dependencies":[],"fileDependencies":[],"size":24,"hash":"04e2f69e92e27fe6b8834deb00d41de6","srcHash":"04e2f69e92e27fe6b8834deb00d41de6","service":"defaultService"}},"1c202aR-5df41cE-dad173S-efb790R":{"path":"1c/1c202aR-5df41cE-dad173S-efb790R.heavyRes","tempPath":"","meta":{"uuid":"1c202aR-5df41cE-dad173S-efb790R","importSettings":{},"ver":"1","dependencies":["23502aR-daafd4E-57b165S-101c8bR"],"fileDependencies":["d73f52F-772699I-9ae934L-30c2e1E"],"size":198,"srcHash":"aeff2b739139800d70f4e71e8911a641","hash":"aeff2b739139800d70f4e71e8911a641","service":"defaultService"}},"1e502eF-4e6cbbI-b9ecabL-e1e51cE":{"path":"1e/1e502eF-4e6cbbI-b9ecabL-e1e51cE.mesh.bin","tempPath":"","meta":{"uuid":"1e502eF-4e6cbbI-b9ecabL-e1e51cE","importSettings":{"inheritGroupId":true,"groupId":"","isEntries":"false","recursiveSetEntries":true,"isPackInBuildIn":"false"},"ver":"1","size":35792,"service":"defaultService","hash":"5ddbbf824c78717e440a840af59d192e","srcHash":"5ddbbf824c78717e440a840af59d192e","dependencies":[],"fileDependencies":[]}},"1f1b68R-1fbe93E-854effS-d9999aR":{"path":"1f/1f1b68R-1fbe93E-854effS-d9999aR.texture2d","tempPath":"","meta":{"uuid":"1f1b68R-1fbe93E-854effS-d9999aR","hash":"b48e3fcfafb61b0065e017de0f5a2593","srcHash":"b48e3fcfafb61b0065e017de0f5a2593","importSettings":{"textureData":{"data":{"width":256,"height":256,"sRGB":true,"needPremultiplyAlpha":false,"useMipmap":true,"mipmap":9,"wrapU":1,"wrapV":1,"filterMode":2,"pixelFormat":2,"anisoLevel":1},"editorInfo":{"assetVersion":2,"enableCompress":true}},"__localId":{"texture2d":1},"metaMTime":1604661026018,"inheritGroupId":true,"groupId":"","isEntries":"false","recursiveSetEntries":true,"isPackInBuildIn":"false"},"dependencies":[],"fileDependencies":["5365ffF-bf862fI-d1d566L-19361aE"],"size":219,"service":"defaultService"}},"1fe445R-5afe4eE-682922S-fe7185R":{"path":"1f/1fe445R-5afe4eE-682922S-fe7185R.texture2d","tempPath":"","meta":{"uuid":"1fe445R-5afe4eE-682922S-fe7185R","hash":"f6edc64826d253ce3b3bcf8305bc5c61","srcHash":"f6edc64826d253ce3b3bcf8305bc5c61","importSettings":{"textureData":{"data":{"width":512,"height":512,"sRGB":true,"needPremultiplyAlpha":false,"useMipmap":true,"mipmap":10,"wrapU":1,"wrapV":1,"filterMode":2,"pixelFormat":2,"anisoLevel":1},"editorInfo":{"assetVersion":2,"enableCompress":true}},"__localId":{"texture2d":1},"metaMTime":1604661026008,"inheritGroupId":true,"groupId":"","isEntries":"false","recursiveSetEntries":true,"isPackInBuildIn":"false"},"dependencies":[],"fileDependencies":["e243c4F-e773dfI-1f03ccL-ef8048E"],"size":220,"service":"defaultService"}},"226500R-76d383E-2d9ffdS-37b307R":{"path":"22/226500R-76d383E-2d9ffdS-37b307R.heavyRes","tempPath":"","meta":{"uuid":"226500R-76d383E-2d9ffdS-37b307R","importSettings":{},"ver":"1","dependencies":["a1c543R-06b0b6E-2320a5S-ea08fbR"],"fileDependencies":["bc8d98F-b4e368I-92bb6dL-8d40d5E"],"size":188,"srcHash":"66a79cf8ac7c7c84c590609358a597aa","hash":"66a79cf8ac7c7c84c590609358a597aa","service":"defaultService"}},"23502aR-daafd4E-57b165S-101c8bR":{"path":"23/23502aR-daafd4E-57b165S-101c8bR.texture2d","tempPath":"","meta":{"uuid":"23502aR-daafd4E-57b165S-101c8bR","hash":"4c973d6a4c3f0560c610d8ab4b912337","srcHash":"4c973d6a4c3f0560c610d8ab4b912337","importSettings":{"textureData":{"data":{"width":256,"height":256,"sRGB":true,"needPremultiplyAlpha":false,"useMipmap":true,"mipmap":9,"wrapU":1,"wrapV":1,"filterMode":2,"pixelFormat":2,"anisoLevel":1},"editorInfo":{"assetVersion":2,"enableCompress":true}},"__localId":{"texture2d":1},"metaMTime":1604661025956,"inheritGroupId":true,"groupId":"","isEntries":"false","recursiveSetEntries":true,"isPackInBuildIn":"false"},"dependencies":[],"fileDependencies":["d73f52F-772699I-9ae934L-30c2e1E"],"size":219,"service":"defaultService"}},"25d7c7F-9ebd7cI-530863L-915415E":{"path":"25/25d7c7F-9ebd7cI-530863L-915415E.bin","tempPath":"","meta":{"uuid":"25d7c7F-9ebd7cI-530863L-915415E","importSettings":{"relatedSrcUuid":"a58ceaR-3e3505E-6029d5S-8e6761R"},"ver":"1","dependencies":[],"fileDependencies":[],"size":896,"hash":"93d5afb7fcbcce93ee41200255aaf9d6","srcHash":"93d5afb7fcbcce93ee41200255aaf9d6","service":"defaultService"}},"268c93R-d45186E-44ac03S-3a3021R":{"path":"26/268c93R-d45186E-44ac03S-3a3021R.heavyRes","tempPath":"","meta":{"uuid":"268c93R-d45186E-44ac03S-3a3021R","importSettings":{},"ver":"1","dependencies":["1f1b68R-1fbe93E-854effS-d9999aR"],"fileDependencies":["5365ffF-bf862fI-d1d566L-19361aE"],"size":190,"srcHash":"dfd80c8ef3e72cffffb82f88a23ace6e","hash":"dfd80c8ef3e72cffffb82f88a23ace6e","service":"defaultService"}},"26ba62F-50012dI-0c9a85L-bd4a63E":{"path":"26/26ba62F-50012dI-0c9a85L-bd4a63E.bin","tempPath":"","meta":{"uuid":"26ba62F-50012dI-0c9a85L-bd4a63E","importSettings":{"relatedSrcUuid":"54c366R-18c89dE-201764S-f4ffb9R"},"ver":"1","dependencies":[],"fileDependencies":[],"size":1036,"hash":"34d10f2b4c987dd8a9e23659cc5898a1","srcHash":"34d10f2b4c987dd8a9e23659cc5898a1","service":"defaultService"}},"2b30c7R-e0996fE-6d4637S-d3e40eR":{"path":"2b/2b30c7R-e0996fE-6d4637S-d3e40eR.mat","tempPath":"","meta":{"uuid":"2b30c7R-e0996fE-6d4637S-d3e40eR","importSettings":{"inheritGroupId":true,"groupId":"","isEntries":"false","recursiveSetEntries":true,"isPackInBuildIn":"false"},"ver":"1","size":490,"service":"defaultService","hash":"0ecc001d360bcbb1ce86cdc883aad4a6","dependencies":["0946f4R-130a1eE-f1c506S-9de1d3R","c7fb21R-abb109E-a8e91bS-54b4baR"],"fileDependencies":[],"srcHash":"0ecc001d360bcbb1ce86cdc883aad4a6"}},"2fd85cR-19d866E-f6096fS-d4b556R":{"path":"2f/2fd85cR-19d866E-f6096fS-d4b556R.heavyRes","tempPath":"","meta":{"uuid":"2fd85cR-19d866E-f6096fS-d4b556R","importSettings":{},"ver":"1","dependencies":["a3b552R-3ab22fE-1af925S-17deb8R"],"fileDependencies":["a9dadbF-357f88I-e647caL-128c85E"],"size":188,"srcHash":"45d6040ce45e5233fc065691e525a42b","hash":"45d6040ce45e5233fc065691e525a42b","service":"defaultService"}},"312907R-2fedb5E-9e0577S-f1f3f4R":{"path":"31/312907R-2fedb5E-9e0577S-f1f3f4R.heavyRes","tempPath":"","meta":{"uuid":"312907R-2fedb5E-9e0577S-f1f3f4R","importSettings":{},"ver":"1","dependencies":["7479ffR-73c9baE-02cb32S-8ec50fR"],"fileDependencies":["18c880F-79fd53I-da12d9L-0be16fE"],"size":190,"srcHash":"7f2f35a11e3031f436701f4fdea85474","hash":"7f2f35a11e3031f436701f4fdea85474","service":"defaultService"}},"3424f3R-0ccd55E-d361efS-047b6dR":{"path":"34/3424f3R-0ccd55E-d361efS-047b6dR.spriteframe","tempPath":"","meta":{"uuid":"3424f3R-0ccd55E-d361efS-047b6dR","importSettings":{"inheritGroupId":true,"groupId":"","isEntries":"false","recursiveSetEntries":true,"isPackInBuildIn":"false"},"ver":"1","dependencies":["8f01e5R-9af7bcE-e63d91S-42e127R"],"fileDependencies":[],"size":66,"service":"defaultService","hash":"36c08093a888145b86ad3926644fed70","srcHash":"36c08093a888145b86ad3926644fed70"}},"399e1cR-833f5dE-ebb320S-eafec3R":{"path":"39/399e1cR-833f5dE-ebb320S-eafec3R.mat","tempPath":"","meta":{"uuid":"399e1cR-833f5dE-ebb320S-eafec3R","importSettings":{"inheritGroupId":true,"groupId":"","isEntries":"false","recursiveSetEntries":true,"isPackInBuildIn":"false"},"ver":"1","size":251,"service":"defaultService","hash":"fc2d6be2bf309be6a2f518970570c251","dependencies":["d599e1R-1b7d8bE-cd434fS-9ec036R","f75b6eR-26db4aE-74d251S-b121f3R"],"fileDependencies":[],"srcHash":"fc2d6be2bf309be6a2f518970570c251"}},"3a5ee4R-a448cfE-08b355S-05f513R":{"path":"3a/3a5ee4R-a448cfE-08b355S-05f513R.heavyRes","tempPath":"","meta":{"uuid":"3a5ee4R-a448cfE-08b355S-05f513R","importSettings":{},"ver":"1","dependencies":["3e39f0R-af5af9E-882fb4S-35be2eR"],"fileDependencies":["4eabb1F-a6d6acI-18916bL-c22216E"],"size":193,"srcHash":"d61afed279aa82adf18f2f9245df4578","hash":"d61afed279aa82adf18f2f9245df4578","service":"defaultService"}},"3dc2a0R-26750aE-e3e9f1S-92b448R":{"path":"3d/3dc2a0R-26750aE-e3e9f1S-92b448R.scene","tempPath":"","meta":{"uuid":"3dc2a0R-26750aE-e3e9f1S-92b448R","importSettings":{"inheritGroupId":true,"groupId":"","isEntries":"true","recursiveSetEntries":true,"isPackInBuildIn":"false"},"ver":"1","dependencies":["3424f3R-0ccd55E-d361efS-047b6dR","b196f7R-769516E-e4b208S-3ff571R","0708fcR-f9d3a0E-d860ceS-176f68R","4067f0R-39bb01E-e28ce3S-842a98R","bd54dcR-0b4fc7E-6416f5S-3e7770R"],"fileDependencies":[],"size":3379,"srcHash":"1c0eb6a76e739a5aa96e23cb3b16aba1","service":"defaultService","hash":"1c0eb6a76e739a5aa96e23cb3b16aba1"}},"3e39f0R-af5af9E-882fb4S-35be2eR":{"path":"3e/3e39f0R-af5af9E-882fb4S-35be2eR.texture2d","tempPath":"","meta":{"uuid":"3e39f0R-af5af9E-882fb4S-35be2eR","hash":"2573c50b6a2177f518c47199f4dcf91c","srcHash":"2573c50b6a2177f518c47199f4dcf91c","importSettings":{"textureData":{"data":{"width":512,"height":512,"sRGB":true,"needPremultiplyAlpha":false,"useMipmap":true,"mipmap":10,"wrapU":1,"wrapV":1,"filterMode":2,"pixelFormat":2,"anisoLevel":1},"editorInfo":{"assetVersion":2,"enableCompress":true}},"__localId":{"texture2d":1},"metaMTime":1604661026000,"inheritGroupId":true,"groupId":"","isEntries":"false","recursiveSetEntries":true,"isPackInBuildIn":"false"},"dependencies":[],"fileDependencies":["4eabb1F-a6d6acI-18916bL-c22216E"],"size":220,"service":"defaultService"}},"405eabR-ca288aE-5bf4f3S-3b3bd3R":{"path":"40/405eabR-ca288aE-5bf4f3S-3b3bd3R.effect","tempPath":"","meta":{"uuid":"405eabR-ca288aE-5bf4f3S-3b3bd3R","importSettings":{"inheritGroupId":true,"groupId":"","isEntries":"true","recursiveSetEntries":true,"isPackInBuildIn":"true"},"dependencies":[],"fileDependencies":[],"size":5098,"service":"defaultService","srcHash":"9c772b3037a87931e7d082838cd9c4d8","hash":"9c772b3037a87931e7d082838cd9c4d8"}},"40f525R-1e74d3E-593b5cS-9bdf5bR":{"path":"40/40f525R-1e74d3E-593b5cS-9bdf5bR.heavyRes","tempPath":"","meta":{"uuid":"40f525R-1e74d3E-593b5cS-9bdf5bR","importSettings":{},"ver":"1","dependencies":["7479ffR-73c9baE-02cb32S-8ec50fR"],"fileDependencies":["18c880F-79fd53I-da12d9L-0be16fE"],"size":198,"srcHash":"95fe924c59070283d2ae518d527be5d3","hash":"95fe924c59070283d2ae518d527be5d3","service":"defaultService"}},"4496a9F-f5e408I-368031L-edae2eE":{"path":"44/4496a9F-f5e408I-368031L-edae2eE.png","tempPath":"","meta":{"uuid":"4496a9F-f5e408I-368031L-edae2eE","hash":"718fc853eade8b90bbaa0a57ec472a7a","srcHash":"718fc853eade8b90bbaa0a57ec472a7a","importSettings":{"textureData":{"data":{"width":400,"height":400,"sRGB":true,"needPremultiplyAlpha":false,"useMipmap":false,"mipmap":1,"wrapU":2,"wrapV":2,"filterMode":0,"pixelFormat":2,"anisoLevel":1,"wrapS":2,"wrapT":2},"editorInfo":{"assetVersion":2,"enableCompress":true}},"__localId":{"texture2d":1},"metaMTime":1604661026096,"inheritGroupId":true,"groupId":"","isEntries":"false","recursiveSetEntries":true,"isPackInBuildIn":"false"},"dependencies":[],"fileDependencies":[],"size":14904,"service":"defaultService"}},"491908R-b8092bE-22e989S-c825e2R":{"path":"49/491908R-b8092bE-22e989S-c825e2R.heavyRes","tempPath":"","meta":{"uuid":"491908R-b8092bE-22e989S-c825e2R","importSettings":{},"ver":"1","dependencies":["b0d843R-2c7dbeE-16080dS-63ada6R"],"fileDependencies":["5a7b80F-d1c0a9I-7018cbL-2b13a5E"],"size":198,"srcHash":"f0fb40a2910c9fb3e8b7c22cf3eca272","hash":"f0fb40a2910c9fb3e8b7c22cf3eca272","service":"defaultService"}},"4ab089R-47a72dE-831189S-098257R":{"path":"4a/4ab089R-47a72dE-831189S-098257R.heavyRes","tempPath":"","meta":{"uuid":"4ab089R-47a72dE-831189S-098257R","importSettings":{},"ver":"1","dependencies":["59b5dcR-544364E-bb2413S-f769c0R"],"fileDependencies":["8d5288F-6280aeI-39e031L-a83085E"],"size":190,"srcHash":"495b926099112dea8ed5e6dcb690e9b5","hash":"495b926099112dea8ed5e6dcb690e9b5","service":"defaultService"}},"4c6bffF-f982d1I-27764fL-e95746E":{"path":"4c/4c6bffF-f982d1I-27764fL-e95746E.mesh.bin","tempPath":"","meta":{"uuid":"4c6bffF-f982d1I-27764fL-e95746E","importSettings":{"inheritGroupId":true,"groupId":"","isEntries":"false","recursiveSetEntries":true,"isPackInBuildIn":"false"},"ver":"1","size":33448,"service":"defaultService","hash":"4bbbae61dc4671760b19540fa8109178","srcHash":"4bbbae61dc4671760b19540fa8109178","dependencies":[],"fileDependencies":[]}},"4eabb1F-a6d6acI-18916bL-c22216E":{"path":"4e/4eabb1F-a6d6acI-18916bL-c22216E.jpg","tempPath":"","meta":{"uuid":"4eabb1F-a6d6acI-18916bL-c22216E","hash":"3a037253eb3ab9e9c1f7090594d7611c","srcHash":"3a037253eb3ab9e9c1f7090594d7611c","importSettings":{"textureData":{"data":{"width":512,"height":512,"sRGB":true,"needPremultiplyAlpha":false,"useMipmap":true,"mipmap":10,"wrapU":1,"wrapV":1,"filterMode":2,"pixelFormat":2,"anisoLevel":1},"editorInfo":{"assetVersion":2,"enableCompress":true}},"__localId":{"texture2d":1},"metaMTime":1604661026000,"inheritGroupId":true,"groupId":"","isEntries":"false","recursiveSetEntries":true,"isPackInBuildIn":"false"},"dependencies":[],"fileDependencies":[],"size":28559,"service":"defaultService"}},"5365ffF-bf862fI-d1d566L-19361aE":{"path":"53/5365ffF-bf862fI-d1d566L-19361aE.png","tempPath":"","meta":{"uuid":"5365ffF-bf862fI-d1d566L-19361aE","hash":"0733906956b123426a065533a0ce56f7","srcHash":"0733906956b123426a065533a0ce56f7","importSettings":{"textureData":{"data":{"width":256,"height":256,"sRGB":true,"needPremultiplyAlpha":false,"useMipmap":true,"mipmap":9,"wrapU":1,"wrapV":1,"filterMode":2,"pixelFormat":2,"anisoLevel":1},"editorInfo":{"assetVersion":2,"enableCompress":true}},"__localId":{"texture2d":1},"metaMTime":1604661026018,"inheritGroupId":true,"groupId":"","isEntries":"false","recursiveSetEntries":true,"isPackInBuildIn":"false"},"dependencies":[],"fileDependencies":[],"size":107444,"service":"defaultService"}},"54c366R-18c89dE-201764S-f4ffb9R":{"path":"54/54c366R-18c89dE-201764S-f4ffb9R.prefab","tempPath":"","meta":{"uuid":"54c366R-18c89dE-201764S-f4ffb9R","importSettings":{"groupId":"","inheritGroupId":true,"isEntries":"true","recursiveSetEntries":true,"isPackInBuildIn":"false"},"ver":"1","size":5345,"srcHash":"2b85c354f514804609ccf93662d337bd","service":"defaultService","dependencies":["bd533cR-aa78e6E-b47bfbS-d61933R","6912a0R-a4bbe6E-b24218S-481842R","d4f4caR-d6008aE-e8c511S-81b8d1R"],"fileDependencies":["c4e573F-7a99a3I-8c94b1L-ac6028E","18dcebF-c71d74I-c1de04L-03fa2eE","f490b7F-c850f8I-8fb042L-320b34E","26ba62F-50012dI-0c9a85L-bd4a63E"],"hash":"2b85c354f514804609ccf93662d337bd"}},"582673F-171a43I-c58343L-edda50E":{"path":"58/582673F-171a43I-c58343L-edda50E.bin","tempPath":"","meta":{"uuid":"582673F-171a43I-c58343L-edda50E","importSettings":{"relatedSrcUuid":"9b0f03R-85c949E-1f86daS-4dccd9R"},"ver":"1","dependencies":[],"fileDependencies":[],"size":476,"hash":"9a4175287f7ebd764520e78cec71bc6b","srcHash":"9a4175287f7ebd764520e78cec71bc6b","service":"defaultService"}},"59b5dcR-544364E-bb2413S-f769c0R":{"path":"59/59b5dcR-544364E-bb2413S-f769c0R.texture2d","tempPath":"","meta":{"uuid":"59b5dcR-544364E-bb2413S-f769c0R","hash":"5b55a0beff5fad1bce82decf295839b1","srcHash":"5b55a0beff5fad1bce82decf295839b1","importSettings":{"textureData":{"data":{"width":400,"height":400,"sRGB":true,"needPremultiplyAlpha":false,"useMipmap":false,"mipmap":1,"wrapU":2,"wrapV":2,"filterMode":0,"pixelFormat":2,"anisoLevel":1,"wrapS":2,"wrapT":2},"editorInfo":{"assetVersion":2,"enableCompress":true}},"__localId":{"texture2d":1},"metaMTime":1604661026087,"inheritGroupId":true,"groupId":"","isEntries":"false","recursiveSetEntries":true,"isPackInBuildIn":"false"},"dependencies":[],"fileDependencies":["8d5288F-6280aeI-39e031L-a83085E"],"size":240,"service":"defaultService"}},"5a7b80F-d1c0a9I-7018cbL-2b13a5E":{"path":"5a/5a7b80F-d1c0a9I-7018cbL-2b13a5E.png","tempPath":"","meta":{"uuid":"5a7b80F-d1c0a9I-7018cbL-2b13a5E","hash":"d4229edc0c7a2eaf2f82ce66e21696df","srcHash":"d4229edc0c7a2eaf2f82ce66e21696df","importSettings":{"textureData":{"data":{"width":128,"height":128,"sRGB":true,"needPremultiplyAlpha":false,"useMipmap":true,"mipmap":8,"wrapU":1,"wrapV":1,"filterMode":2,"pixelFormat":2,"anisoLevel":1},"editorInfo":{"assetVersion":2,"enableCompress":true}},"__localId":{"texture2d":1},"metaMTime":1604661025944,"inheritGroupId":true,"groupId":"","isEntries":"false","recursiveSetEntries":true,"isPackInBuildIn":"false"},"dependencies":[],"fileDependencies":[],"size":9671,"service":"defaultService"}},"5adac4R-d425a7E-2fb2e1S-eba36aR":{"path":"5a/5adac4R-d425a7E-2fb2e1S-eba36aR.heavyRes","tempPath":"","meta":{"uuid":"5adac4R-d425a7E-2fb2e1S-eba36aR","importSettings":{},"ver":"1","dependencies":["1f1b68R-1fbe93E-854effS-d9999aR"],"fileDependencies":["5365ffF-bf862fI-d1d566L-19361aE"],"size":188,"srcHash":"a7060681fca85691dfc40418a931326d","hash":"a7060681fca85691dfc40418a931326d","service":"defaultService"}},"5cad53R-49573fE-feed6dS-0774efR":{"path":"5c/5cad53R-49573fE-feed6dS-0774efR.heavyRes","tempPath":"","meta":{"uuid":"5cad53R-49573fE-feed6dS-0774efR","importSettings":{},"ver":"1","dependencies":["1fe445R-5afe4eE-682922S-fe7185R"],"fileDependencies":["e243c4F-e773dfI-1f03ccL-ef8048E"],"size":198,"srcHash":"01627ba2c6700b15b308a734fe816cde","hash":"01627ba2c6700b15b308a734fe816cde","service":"defaultService"}},"627153R-420d14E-a7280bS-6b5573R":{"path":"62/627153R-420d14E-a7280bS-6b5573R.heavyRes","tempPath":"","meta":{"uuid":"627153R-420d14E-a7280bS-6b5573R","importSettings":{},"ver":"1","dependencies":["23502aR-daafd4E-57b165S-101c8bR"],"fileDependencies":["d73f52F-772699I-9ae934L-30c2e1E"],"size":188,"srcHash":"2d040627e04497de5633415a72f876a6","hash":"2d040627e04497de5633415a72f876a6","service":"defaultService"}},"67a51fR-b43d36E-1b75cdS-15dfafR":{"path":"67/67a51fR-b43d36E-1b75cdS-15dfafR.mat","tempPath":"","meta":{"uuid":"67a51fR-b43d36E-1b75cdS-15dfafR","importSettings":{"inheritGroupId":true,"groupId":"","isEntries":"false","recursiveSetEntries":true,"isPackInBuildIn":"false"},"ver":"1","size":491,"service":"defaultService","hash":"71f543bc98e388f65dda310c833c7315","dependencies":["9d6ea7R-86fc6fE-1102a6S-fa9bb1R","c7fb21R-abb109E-a8e91bS-54b4baR"],"fileDependencies":[],"srcHash":"71f543bc98e388f65dda310c833c7315"}},"6881abR-d42411E-52cc89S-d5fd62R":{"path":"68/6881abR-d42411E-52cc89S-d5fd62R.heavyRes","tempPath":"","meta":{"uuid":"6881abR-d42411E-52cc89S-d5fd62R","importSettings":{},"ver":"1","dependencies":["c5d410R-b8a879E-2599bcS-5680ddR"],"fileDependencies":["0a74a6F-e91e17I-33a59bL-16e923E"],"size":190,"srcHash":"0832be1290f6fe3d97d7ee56df39ac5c","hash":"0832be1290f6fe3d97d7ee56df39ac5c","service":"defaultService"}},"6912a0R-a4bbe6E-b24218S-481842R":{"path":"69/6912a0R-a4bbe6E-b24218S-481842R.mesh","tempPath":"","meta":{"uuid":"6912a0R-a4bbe6E-b24218S-481842R","importSettings":{"inheritGroupId":true,"groupId":"","isEntries":"false","recursiveSetEntries":true,"isPackInBuildIn":"false"},"ver":"1","size":379,"service":"defaultService","hash":"c24df9909fb8093bb7b6295a08f41e80","dependencies":[],"fileDependencies":["4c6bffF-f982d1I-27764fL-e95746E"],"srcHash":"c24df9909fb8093bb7b6295a08f41e80"}},"700bbdR-324afbE-592f9aS-0c03eaR":{"path":"70/700bbdR-324afbE-592f9aS-0c03eaR.heavyRes","tempPath":"","meta":{"uuid":"700bbdR-324afbE-592f9aS-0c03eaR","importSettings":{},"ver":"1","dependencies":["a5d758R-1c18d1E-050173S-f6814bR"],"fileDependencies":["4496a9F-f5e408I-368031L-edae2eE"],"size":198,"srcHash":"1f82c48c505a5381341900c90c679587","hash":"1f82c48c505a5381341900c90c679587","service":"defaultService"}},"716ea5R-feb632E-cf465eS-a5bb69R":{"path":"71/716ea5R-feb632E-cf465eS-a5bb69R.heavyRes","tempPath":"","meta":{"uuid":"716ea5R-feb632E-cf465eS-a5bb69R","importSettings":{},"ver":"1","dependencies":["c5d410R-b8a879E-2599bcS-5680ddR"],"fileDependencies":["0a74a6F-e91e17I-33a59bL-16e923E"],"size":188,"srcHash":"10dcd7c200dbeb70e8b628cb7797b18a","hash":"10dcd7c200dbeb70e8b628cb7797b18a","service":"defaultService"}},"729319R-1fb2aaE-d455e3S-858c62R":{"path":"72/729319R-1fb2aaE-d455e3S-858c62R.mat","tempPath":"","meta":{"uuid":"729319R-1fb2aaE-d455e3S-858c62R","importSettings":{"inheritGroupId":true,"groupId":"","isEntries":"false","recursiveSetEntries":true,"isPackInBuildIn":"false"},"ver":"1","size":427,"service":"defaultService","hash":"a4b4affec1b27b4b49b67cf7d2e9525b","dependencies":["e1cc29R-ba94e7E-111661S-d09925R","c7fb21R-abb109E-a8e91bS-54b4baR"],"fileDependencies":[],"srcHash":"a4b4affec1b27b4b49b67cf7d2e9525b"}},"734ba6R-018bc5E-4b5cfeS-31cea8R":{"path":"73/734ba6R-018bc5E-4b5cfeS-31cea8R.heavyRes","tempPath":"","meta":{"uuid":"734ba6R-018bc5E-4b5cfeS-31cea8R","importSettings":{},"ver":"1","dependencies":["a3b552R-3ab22fE-1af925S-17deb8R"],"fileDependencies":["a9dadbF-357f88I-e647caL-128c85E"],"size":190,"srcHash":"ebb7a10f8a2088cb0f240f2a6f36baf1","hash":"ebb7a10f8a2088cb0f240f2a6f36baf1","service":"defaultService"}},"7479ffR-73c9baE-02cb32S-8ec50fR":{"path":"74/7479ffR-73c9baE-02cb32S-8ec50fR.texture2d","tempPath":"","meta":{"uuid":"7479ffR-73c9baE-02cb32S-8ec50fR","hash":"b3ff7474a83b53ce982631712577c243","srcHash":"b3ff7474a83b53ce982631712577c243","importSettings":{"textureData":{"data":{"width":256,"height":256,"sRGB":true,"needPremultiplyAlpha":false,"useMipmap":false,"mipmap":1,"wrapU":2,"wrapV":2,"filterMode":1,"pixelFormat":2,"anisoLevel":1},"editorInfo":{"assetVersion":2,"enableCompress":true}},"__localId":{"texture2d":1},"metaMTime":1604661025967,"inheritGroupId":true,"groupId":"","isEntries":"false","recursiveSetEntries":true,"isPackInBuildIn":"false"},"dependencies":[],"fileDependencies":["18c880F-79fd53I-da12d9L-0be16fE"],"size":220,"service":"defaultService"}},"769610R-923901E-302c63S-76c641R":{"path":"76/769610R-923901E-302c63S-76c641R.effect","tempPath":"","meta":{"uuid":"769610R-923901E-302c63S-76c641R","importSettings":{"inheritGroupId":true,"groupId":"","isEntries":"true","recursiveSetEntries":true,"isPackInBuildIn":"true"},"dependencies":[],"fileDependencies":[],"size":2170,"service":"defaultService","srcHash":"b3da5970be5438477e44d716b1f3c14b","hash":"b3da5970be5438477e44d716b1f3c14b"}},"7a15b0R-344e50E-d116e1S-d3be4aR":{"path":"7a/7a15b0R-344e50E-d116e1S-d3be4aR.heavyRes","tempPath":"","meta":{"uuid":"7a15b0R-344e50E-d116e1S-d3be4aR","importSettings":{},"ver":"1","dependencies":["a1c543R-06b0b6E-2320a5S-ea08fbR"],"fileDependencies":["bc8d98F-b4e368I-92bb6dL-8d40d5E"],"size":190,"srcHash":"09000a60d504328817248ce230ea8d51","hash":"09000a60d504328817248ce230ea8d51","service":"defaultService"}},"822a17R-a8d0cfE-45d126S-6f7b6bR":{"path":"82/822a17R-a8d0cfE-45d126S-6f7b6bR.effect","tempPath":"","meta":{"uuid":"822a17R-a8d0cfE-45d126S-6f7b6bR","importSettings":{"inheritGroupId":true,"groupId":"","isEntries":"true","recursiveSetEntries":true,"isPackInBuildIn":"true"},"dependencies":[],"fileDependencies":[],"size":2337,"service":"defaultService","srcHash":"cd26aa9fad546f1f7753e3adf39d5fb2","hash":"cd26aa9fad546f1f7753e3adf39d5fb2"}},"829371R-746a9dE-7bdde1S-8aaa33R":{"path":"82/829371R-746a9dE-7bdde1S-8aaa33R.mat","tempPath":"","meta":{"uuid":"829371R-746a9dE-7bdde1S-8aaa33R","importSettings":{"inheritGroupId":true,"groupId":"","isEntries":"false","recursiveSetEntries":true,"isPackInBuildIn":"false"},"ver":"1","size":427,"service":"defaultService","hash":"19845b64a931963c967123c971061fbe","dependencies":["17bac2R-696b9eE-cce134S-b706b8R","c7fb21R-abb109E-a8e91bS-54b4baR"],"fileDependencies":[],"srcHash":"19845b64a931963c967123c971061fbe"}},"893db1R-41c1d0E-7510c3S-8b5dd5R":{"path":"89/893db1R-41c1d0E-7510c3S-8b5dd5R.heavyRes","tempPath":"","meta":{"uuid":"893db1R-41c1d0E-7510c3S-8b5dd5R","importSettings":{},"ver":"1","dependencies":["59b5dcR-544364E-bb2413S-f769c0R"],"fileDependencies":["8d5288F-6280aeI-39e031L-a83085E"],"size":198,"srcHash":"8acf8a0268f7634595816983e1d986bf","hash":"8acf8a0268f7634595816983e1d986bf","service":"defaultService"}},"894015R-3f2fd8E-9fcebcS-6a181fR":{"path":"89/894015R-3f2fd8E-9fcebcS-6a181fR.texture2d","tempPath":"","meta":{"uuid":"894015R-3f2fd8E-9fcebcS-6a181fR","hash":"d84f04b7b8d3ffb84097311aa6f528fc","srcHash":"d84f04b7b8d3ffb84097311aa6f528fc","importSettings":{"textureData":{"data":{"width":26,"height":37,"sRGB":true,"needPremultiplyAlpha":false,"useMipmap":false,"mipmap":1,"wrapU":2,"wrapV":2,"filterMode":0,"pixelFormat":2,"anisoLevel":1},"editorInfo":{"assetVersion":2,"enableCompress":true}},"__localId":{"texture2d":1},"metaMTime":1604661026035,"inheritGroupId":true,"groupId":"","isEntries":"false","recursiveSetEntries":true,"isPackInBuildIn":"false"},"dependencies":[],"fileDependencies":["0afeedF-26b84aI-dfda01L-b682c6E"],"size":218,"service":"defaultService"}},"8a358aR-d540abE-80889bS-1c7492R":{"path":"8a/8a358aR-d540abE-80889bS-1c7492R.mesh","tempPath":"","meta":{"uuid":"8a358aR-d540abE-80889bS-1c7492R","importSettings":{"inheritGroupId":true,"groupId":"","isEntries":"false","recursiveSetEntries":true,"isPackInBuildIn":"false"},"ver":"1","size":385,"service":"defaultService","hash":"cd522e8ff64fd10cd292412097d24b2f","dependencies":[],"fileDependencies":["96a407F-58ae2bI-6b8da7L-c1239bE"],"srcHash":"cd522e8ff64fd10cd292412097d24b2f"}},"8d5288F-6280aeI-39e031L-a83085E":{"path":"8d/8d5288F-6280aeI-39e031L-a83085E.png","tempPath":"","meta":{"uuid":"8d5288F-6280aeI-39e031L-a83085E","hash":"51ce6840be64eefe6dd8ffed4def6e5f","srcHash":"51ce6840be64eefe6dd8ffed4def6e5f","importSettings":{"textureData":{"data":{"width":400,"height":400,"sRGB":true,"needPremultiplyAlpha":false,"useMipmap":false,"mipmap":1,"wrapU":2,"wrapV":2,"filterMode":0,"pixelFormat":2,"anisoLevel":1,"wrapS":2,"wrapT":2},"editorInfo":{"assetVersion":2,"enableCompress":true}},"__localId":{"texture2d":1},"metaMTime":1604661026087,"inheritGroupId":true,"groupId":"","isEntries":"false","recursiveSetEntries":true,"isPackInBuildIn":"false"},"dependencies":[],"fileDependencies":[],"size":23040,"service":"defaultService"}},"8f38abF-5a3618I-4830f0L-aad17dE":{"path":"8f/8f38abF-5a3618I-4830f0L-aad17dE.bin","tempPath":"","meta":{"uuid":"8f38abF-5a3618I-4830f0L-aad17dE","importSettings":{"relatedSrcUuid":"a58ceaR-3e3505E-6029d5S-8e6761R"},"ver":"1","dependencies":[],"fileDependencies":[],"size":1036,"hash":"aa5ceea3739f90db4323d3c834d2b369","srcHash":"aa5ceea3739f90db4323d3c834d2b369","service":"defaultService"}},"96a407F-58ae2bI-6b8da7L-c1239bE":{"path":"96/96a407F-58ae2bI-6b8da7L-c1239bE.mesh.bin","tempPath":"","meta":{"uuid":"96a407F-58ae2bI-6b8da7L-c1239bE","importSettings":{"inheritGroupId":true,"groupId":"","isEntries":"false","recursiveSetEntries":true,"isPackInBuildIn":"false"},"ver":"1","size":7008,"service":"defaultService","hash":"90ed69f1ae7c60f73d30b662ef3b9310","srcHash":"90ed69f1ae7c60f73d30b662ef3b9310","dependencies":[],"fileDependencies":[]}},"97e344R-55a6c7E-6c9421S-30b926R":{"path":"97/97e344R-55a6c7E-6c9421S-30b926R.scene","tempPath":"","meta":{"uuid":"97e344R-55a6c7E-6c9421S-30b926R","importSettings":{"inheritGroupId":true,"groupId":"","isEntries":"true","recursiveSetEntries":true,"isPackInBuildIn":"false"},"ver":"1","size":4511,"srcHash":"47c2ce8ec7dd9daf027df87298c3a470","service":"defaultService","dependencies":["7504d5R-0bd646E-3ac404S-865d15R","0f3a56R-59ed39E-b1d9bdS-cdafa4R","8a358aR-d540abE-80889bS-1c7492R","f1c742R-b8cfa1E-d89a37S-69a5f6R","2b30c7R-e0996fE-6d4637S-d3e40eR","67a51fR-b43d36E-1b75cdS-15dfafR"],"fileDependencies":[],"hash":"47c2ce8ec7dd9daf027df87298c3a470"}},"998444R-4e8cd1E-52b60bS-d1c239R":{"path":"99/998444R-4e8cd1E-52b60bS-d1c239R.effect","tempPath":"","meta":{"uuid":"998444R-4e8cd1E-52b60bS-d1c239R","importSettings":{"inheritGroupId":true,"groupId":"","isEntries":"true","recursiveSetEntries":true,"isPackInBuildIn":"true"},"dependencies":[],"fileDependencies":[],"size":1202,"service":"defaultService","srcHash":"1aae9595bdbbbebd836b6a13707b4a0f","hash":"1aae9595bdbbbebd836b6a13707b4a0f"}},"9a9882R-d5b03bE-9eaa5dS-cc0cabR":{"path":"9a/9a9882R-d5b03bE-9eaa5dS-cc0cabR.scene","tempPath":"","meta":{"uuid":"9a9882R-d5b03bE-9eaa5dS-cc0cabR","importSettings":{"inheritGroupId":true,"groupId":"","isEntries":"false","recursiveSetEntries":true,"isPackInBuildIn":"false"},"ver":"1","size":3099,"fileDependencies":[],"dependencies":["1c651dR-7719a6E-f316e9S-ea26eeR","d5b210R-110eaeE-1f8b8dS-9d3767R"],"srcHash":"f345788be0cad2dacaefd2f4b27a5de6","service":"defaultService","hash":"f345788be0cad2dacaefd2f4b27a5de6"}},"9b0f03R-85c949E-1f86daS-4dccd9R":{"path":"9b/9b0f03R-85c949E-1f86daS-4dccd9R.prefab","tempPath":"","meta":{"uuid":"9b0f03R-85c949E-1f86daS-4dccd9R","importSettings":{"groupId":"","inheritGroupId":true,"isEntries":"true","recursiveSetEntries":true,"isPackInBuildIn":"false"},"ver":"1","size":3101,"srcHash":"93219d21f744efe265053269030c6b86","service":"defaultService","dependencies":["6912a0R-a4bbe6E-b24218S-481842R","829371R-746a9dE-7bdde1S-8aaa33R","399e1cR-833f5dE-ebb320S-eafec3R"],"fileDependencies":["582673F-171a43I-c58343L-edda50E","062660F-f34be3I-ab1986L-df827cE"],"hash":"93219d21f744efe265053269030c6b86"}},"9c2490R-2200e1E-6274a7S-7c29d2R":{"path":"9c/9c2490R-2200e1E-6274a7S-7c29d2R.heavyRes","tempPath":"","meta":{"uuid":"9c2490R-2200e1E-6274a7S-7c29d2R","importSettings":{},"ver":"1","dependencies":["1fe445R-5afe4eE-682922S-fe7185R"],"fileDependencies":["e243c4F-e773dfI-1f03ccL-ef8048E"],"size":191,"srcHash":"0f3a4f88f2a06ca5ab1c05991f8d018d","hash":"0f3a4f88f2a06ca5ab1c05991f8d018d","service":"defaultService"}},"a015d5R-d0771eE-be912dS-f16081R":{"path":"a0/a015d5R-d0771eE-be912dS-f16081R.effect","tempPath":"","meta":{"uuid":"a015d5R-d0771eE-be912dS-f16081R","importSettings":{"inheritGroupId":true,"groupId":"","isEntries":"true","recursiveSetEntries":true,"isPackInBuildIn":"true"},"dependencies":[],"fileDependencies":[],"size":4033,"service":"defaultService","srcHash":"e6a59a7c7cc62c1bc376051eb0733fd1","hash":"e6a59a7c7cc62c1bc376051eb0733fd1"}},"a1c543R-06b0b6E-2320a5S-ea08fbR":{"path":"a1/a1c543R-06b0b6E-2320a5S-ea08fbR.texture2d","tempPath":"","meta":{"uuid":"a1c543R-06b0b6E-2320a5S-ea08fbR","hash":"1e21fb889df8756eb010b4a4edffc9a6","srcHash":"1e21fb889df8756eb010b4a4edffc9a6","importSettings":{"textureData":{"data":{"width":128,"height":128,"sRGB":true,"needPremultiplyAlpha":false,"useMipmap":true,"mipmap":8,"wrapU":1,"wrapV":1,"filterMode":2,"pixelFormat":2,"anisoLevel":1},"editorInfo":{"assetVersion":2,"enableCompress":true}},"__localId":{"texture2d":1},"metaMTime":1604661025991,"inheritGroupId":true,"groupId":"","isEntries":"false","recursiveSetEntries":true,"isPackInBuildIn":"false"},"dependencies":[],"fileDependencies":["bc8d98F-b4e368I-92bb6dL-8d40d5E"],"size":219,"service":"defaultService"}},"a1faf3R-f20651E-73b036S-d7523cR":{"path":"a1/a1faf3R-f20651E-73b036S-d7523cR.heavyRes","tempPath":"","meta":{"uuid":"a1faf3R-f20651E-73b036S-d7523cR","importSettings":{},"ver":"1","dependencies":["1f1b68R-1fbe93E-854effS-d9999aR"],"fileDependencies":["5365ffF-bf862fI-d1d566L-19361aE"],"size":198,"srcHash":"dbb6c5b5a575debec2330094ba82cf7c","hash":"dbb6c5b5a575debec2330094ba82cf7c","service":"defaultService"}},"a3b552R-3ab22fE-1af925S-17deb8R":{"path":"a3/a3b552R-3ab22fE-1af925S-17deb8R.texture2d","tempPath":"","meta":{"uuid":"a3b552R-3ab22fE-1af925S-17deb8R","hash":"14cdbbcc2d2023f447539690dd227409","srcHash":"14cdbbcc2d2023f447539690dd227409","importSettings":{"textureData":{"data":{"width":128,"height":128,"sRGB":true,"needPremultiplyAlpha":false,"useMipmap":true,"mipmap":8,"wrapU":1,"wrapV":1,"filterMode":2,"pixelFormat":2,"anisoLevel":1},"editorInfo":{"assetVersion":2,"enableCompress":true}},"__localId":{"texture2d":1},"metaMTime":1604661025934,"inheritGroupId":true,"groupId":"","isEntries":"false","recursiveSetEntries":true,"isPackInBuildIn":"false"},"dependencies":[],"fileDependencies":["a9dadbF-357f88I-e647caL-128c85E"],"size":219,"service":"defaultService"}},"a55e68R-bc3721E-f0e2a3S-3202c2R":{"path":"a5/a55e68R-bc3721E-f0e2a3S-3202c2R.heavyRes","tempPath":"","meta":{"uuid":"a55e68R-bc3721E-f0e2a3S-3202c2R","importSettings":{},"ver":"1","dependencies":["b0d843R-2c7dbeE-16080dS-63ada6R"],"fileDependencies":["5a7b80F-d1c0a9I-7018cbL-2b13a5E"],"size":190,"srcHash":"8dd1e46b78cfadf1638326d0eaef5162","hash":"8dd1e46b78cfadf1638326d0eaef5162","service":"defaultService"}},"a58ceaR-3e3505E-6029d5S-8e6761R":{"path":"a5/a58ceaR-3e3505E-6029d5S-8e6761R.prefab","tempPath":"","meta":{"uuid":"a58ceaR-3e3505E-6029d5S-8e6761R","importSettings":{"groupId":"","inheritGroupId":true,"isEntries":"true","recursiveSetEntries":true,"isPackInBuildIn":"false"},"ver":"1","size":4968,"srcHash":"395b7a73f2d60ee6303da6850549453c","service":"defaultService","dependencies":["bd533cR-aa78e6E-b47bfbS-d61933R","6912a0R-a4bbe6E-b24218S-481842R","729319R-1fb2aaE-d455e3S-858c62R","f80ec5R-e5ae6fE-ca3bd1S-f29f09R","0863a5R-27792bE-e2082bS-5a9b9bR"],"fileDependencies":["25d7c7F-9ebd7cI-530863L-915415E","e12986F-a034aaI-4ed379L-e9f86fE","c4e92aF-e8357aI-6c697aL-733475E","8f38abF-5a3618I-4830f0L-aad17dE"],"hash":"395b7a73f2d60ee6303da6850549453c"}},"a5d758R-1c18d1E-050173S-f6814bR":{"path":"a5/a5d758R-1c18d1E-050173S-f6814bR.texture2d","tempPath":"","meta":{"uuid":"a5d758R-1c18d1E-050173S-f6814bR","hash":"e03ae0466b59770170dbb54e109a00a1","srcHash":"e03ae0466b59770170dbb54e109a00a1","importSettings":{"textureData":{"data":{"width":400,"height":400,"sRGB":true,"needPremultiplyAlpha":false,"useMipmap":false,"mipmap":1,"wrapU":2,"wrapV":2,"filterMode":0,"pixelFormat":2,"anisoLevel":1,"wrapS":2,"wrapT":2},"editorInfo":{"assetVersion":2,"enableCompress":true}},"__localId":{"texture2d":1},"metaMTime":1604661026096,"inheritGroupId":true,"groupId":"","isEntries":"false","recursiveSetEntries":true,"isPackInBuildIn":"false"},"dependencies":[],"fileDependencies":["4496a9F-f5e408I-368031L-edae2eE"],"size":240,"service":"defaultService"}},"a89e58R-501dacE-58eef3S-f88a8dR":{"path":"a8/a89e58R-501dacE-58eef3S-f88a8dR.effect","tempPath":"","meta":{"uuid":"a89e58R-501dacE-58eef3S-f88a8dR","importSettings":{"inheritGroupId":true,"groupId":"","isEntries":"true","recursiveSetEntries":true,"isPackInBuildIn":"true"},"dependencies":[],"fileDependencies":[],"size":4013,"service":"defaultService","srcHash":"f39752dec18f3e0be4504e09b9e9b84e","hash":"f39752dec18f3e0be4504e09b9e9b84e"}},"a9dadbF-357f88I-e647caL-128c85E":{"path":"a9/a9dadbF-357f88I-e647caL-128c85E.png","tempPath":"","meta":{"uuid":"a9dadbF-357f88I-e647caL-128c85E","hash":"66b6535e3d8da235726078754c1af829","srcHash":"66b6535e3d8da235726078754c1af829","importSettings":{"textureData":{"data":{"width":128,"height":128,"sRGB":true,"needPremultiplyAlpha":false,"useMipmap":true,"mipmap":8,"wrapU":1,"wrapV":1,"filterMode":2,"pixelFormat":2,"anisoLevel":1},"editorInfo":{"assetVersion":2,"enableCompress":true}},"__localId":{"texture2d":1},"metaMTime":1604661025934,"inheritGroupId":true,"groupId":"","isEntries":"false","recursiveSetEntries":true,"isPackInBuildIn":"false"},"dependencies":[],"fileDependencies":[],"size":17593,"service":"defaultService"}},"b0d843R-2c7dbeE-16080dS-63ada6R":{"path":"b0/b0d843R-2c7dbeE-16080dS-63ada6R.texture2d","tempPath":"","meta":{"uuid":"b0d843R-2c7dbeE-16080dS-63ada6R","hash":"56d6d7ff76b06b48669000fb865eb0b1","srcHash":"56d6d7ff76b06b48669000fb865eb0b1","importSettings":{"textureData":{"data":{"width":128,"height":128,"sRGB":true,"needPremultiplyAlpha":false,"useMipmap":true,"mipmap":8,"wrapU":1,"wrapV":1,"filterMode":2,"pixelFormat":2,"anisoLevel":1},"editorInfo":{"assetVersion":2,"enableCompress":true}},"__localId":{"texture2d":1},"metaMTime":1604661025944,"inheritGroupId":true,"groupId":"","isEntries":"false","recursiveSetEntries":true,"isPackInBuildIn":"false"},"dependencies":[],"fileDependencies":["5a7b80F-d1c0a9I-7018cbL-2b13a5E"],"size":219,"service":"defaultService"}},"b152c1R-75a2cfE-fc6526S-f4a64eR":{"path":"b1/b152c1R-75a2cfE-fc6526S-f4a64eR.heavyRes","tempPath":"","meta":{"uuid":"b152c1R-75a2cfE-fc6526S-f4a64eR","importSettings":{},"ver":"1","dependencies":["1fe445R-5afe4eE-682922S-fe7185R"],"fileDependencies":["e243c4F-e773dfI-1f03ccL-ef8048E"],"size":193,"srcHash":"258220e4687b67902639dc3744c01a3e","hash":"258220e4687b67902639dc3744c01a3e","service":"defaultService"}},"b1c95eR-a964faE-2737a0S-1041a9R":{"path":"b1/b1c95eR-a964faE-2737a0S-1041a9R.heavyRes","tempPath":"","meta":{"uuid":"b1c95eR-a964faE-2737a0S-1041a9R","importSettings":{},"ver":"1","dependencies":["3e39f0R-af5af9E-882fb4S-35be2eR"],"fileDependencies":["4eabb1F-a6d6acI-18916bL-c22216E"],"size":191,"srcHash":"0bde70640266fc9abc5bd4140cfeada4","hash":"0bde70640266fc9abc5bd4140cfeada4","service":"defaultService"}},"b26b56R-cd3c68E-88b4c1S-572256R":{"path":"b2/b26b56R-cd3c68E-88b4c1S-572256R.heavyRes","tempPath":"","meta":{"uuid":"b26b56R-cd3c68E-88b4c1S-572256R","importSettings":{},"ver":"1","dependencies":["894015R-3f2fd8E-9fcebcS-6a181fR"],"fileDependencies":["0afeedF-26b84aI-dfda01L-b682c6E"],"size":198,"srcHash":"82d9fd18ad5f9965895c844ae5c1d604","hash":"82d9fd18ad5f9965895c844ae5c1d604","service":"defaultService"}},"b82c3fR-534936E-11e907S-f664b7R":{"path":"b8/b82c3fR-534936E-11e907S-f664b7R.heavyRes","tempPath":"","meta":{"uuid":"b82c3fR-534936E-11e907S-f664b7R","importSettings":{},"ver":"1","dependencies":["7479ffR-73c9baE-02cb32S-8ec50fR"],"fileDependencies":["18c880F-79fd53I-da12d9L-0be16fE"],"size":188,"srcHash":"2f27447a77b851bf61c52f250826e4c1","hash":"2f27447a77b851bf61c52f250826e4c1","service":"defaultService"}},"bc8d98F-b4e368I-92bb6dL-8d40d5E":{"path":"bc/bc8d98F-b4e368I-92bb6dL-8d40d5E.png","tempPath":"","meta":{"uuid":"bc8d98F-b4e368I-92bb6dL-8d40d5E","hash":"a70a1c99ac78820755d7a8fc44b1d9db","srcHash":"a70a1c99ac78820755d7a8fc44b1d9db","importSettings":{"textureData":{"data":{"width":128,"height":128,"sRGB":true,"needPremultiplyAlpha":false,"useMipmap":true,"mipmap":8,"wrapU":1,"wrapV":1,"filterMode":2,"pixelFormat":2,"anisoLevel":1},"editorInfo":{"assetVersion":2,"enableCompress":true}},"__localId":{"texture2d":1},"metaMTime":1604661025991,"inheritGroupId":true,"groupId":"","isEntries":"false","recursiveSetEntries":true,"isPackInBuildIn":"false"},"dependencies":[],"fileDependencies":[],"size":38767,"service":"defaultService"}},"bd533cR-aa78e6E-b47bfbS-d61933R":{"path":"bd/bd533cR-aa78e6E-b47bfbS-d61933R.mat","tempPath":"","meta":{"uuid":"bd533cR-aa78e6E-b47bfbS-d61933R","importSettings":{"inheritGroupId":true,"groupId":"","isEntries":"false","recursiveSetEntries":true,"isPackInBuildIn":"false"},"ver":"1","size":283,"service":"defaultService","hash":"bea0e13eda5ed759c45e3f541ac1bd75","dependencies":["f75b6eR-26db4aE-74d251S-b121f3R","1af810R-9af831E-5d3ff5S-88d43dR"],"fileDependencies":[],"srcHash":"bea0e13eda5ed759c45e3f541ac1bd75"}},"c4e573F-7a99a3I-8c94b1L-ac6028E":{"path":"c4/c4e573F-7a99a3I-8c94b1L-ac6028E.bin","tempPath":"","meta":{"uuid":"c4e573F-7a99a3I-8c94b1L-ac6028E","importSettings":{"relatedSrcUuid":"54c366R-18c89dE-201764S-f4ffb9R"},"ver":"1","dependencies":[],"fileDependencies":[],"size":896,"hash":"083eea5dc9e19fdf77a6b925d21d4140","srcHash":"083eea5dc9e19fdf77a6b925d21d4140","service":"defaultService"}},"c4e92aF-e8357aI-6c697aL-733475E":{"path":"c4/c4e92aF-e8357aI-6c697aL-733475E.bin","tempPath":"","meta":{"uuid":"c4e92aF-e8357aI-6c697aL-733475E","importSettings":{"relatedSrcUuid":"a58ceaR-3e3505E-6029d5S-8e6761R"},"ver":"1","dependencies":[],"fileDependencies":[],"size":484,"hash":"7e5a511e7b3bb5f1c330b5875726fdaa","srcHash":"7e5a511e7b3bb5f1c330b5875726fdaa","service":"defaultService"}},"c5d410R-b8a879E-2599bcS-5680ddR":{"path":"c5/c5d410R-b8a879E-2599bcS-5680ddR.texture2d","tempPath":"","meta":{"uuid":"c5d410R-b8a879E-2599bcS-5680ddR","hash":"a4d98b417606c7ef0770136539f3f991","srcHash":"a4d98b417606c7ef0770136539f3f991","importSettings":{"textureData":{"data":{"width":128,"height":128,"sRGB":true,"needPremultiplyAlpha":false,"useMipmap":true,"mipmap":8,"wrapU":1,"wrapV":1,"filterMode":2,"pixelFormat":2,"anisoLevel":1},"editorInfo":{"assetVersion":2,"enableCompress":true}},"__localId":{"texture2d":1},"metaMTime":1604661025975,"inheritGroupId":true,"groupId":"","isEntries":"false","recursiveSetEntries":true,"isPackInBuildIn":"false"},"dependencies":[],"fileDependencies":["0a74a6F-e91e17I-33a59bL-16e923E"],"size":219,"service":"defaultService"}},"c7fb21R-abb109E-a8e91bS-54b4baR":{"path":"c7/c7fb21R-abb109E-a8e91bS-54b4baR.effect","tempPath":"","meta":{"uuid":"c7fb21R-abb109E-a8e91bS-54b4baR","importSettings":{"inheritGroupId":true,"groupId":"","isEntries":"false","recursiveSetEntries":true,"isPackInBuildIn":"false"},"dependencies":[],"fileDependencies":[],"size":1086247,"service":"defaultService","srcHash":"63a0ffe6ac4b9d16fbb962ba4cdfd000","hash":"63a0ffe6ac4b9d16fbb962ba4cdfd000"}},"c87a7fR-2b6bddE-e35dfeS-decbc0R":{"path":"c8/c87a7fR-2b6bddE-e35dfeS-decbc0R.heavyRes","tempPath":"","meta":{"uuid":"c87a7fR-2b6bddE-e35dfeS-decbc0R","importSettings":{},"ver":"1","dependencies":["a5d758R-1c18d1E-050173S-f6814bR"],"fileDependencies":["4496a9F-f5e408I-368031L-edae2eE"],"size":190,"srcHash":"332f4464bba0597f1ee48173bf2800ed","hash":"332f4464bba0597f1ee48173bf2800ed","service":"defaultService"}},"d08196R-9a6914E-21f968S-ef5e28R":{"path":"d0/d08196R-9a6914E-21f968S-ef5e28R.effect","tempPath":"","meta":{"uuid":"d08196R-9a6914E-21f968S-ef5e28R","importSettings":{"inheritGroupId":true,"groupId":"","isEntries":"true","recursiveSetEntries":true,"isPackInBuildIn":"true"},"dependencies":[],"fileDependencies":[],"size":1564,"service":"defaultService","srcHash":"8783e9f7fc305970451932837e834d71","hash":"8783e9f7fc305970451932837e834d71"}},"d163f0R-010fbfE-8fc77eS-6f98efR":{"path":"d1/d163f0R-010fbfE-8fc77eS-6f98efR.heavyRes","tempPath":"","meta":{"uuid":"d163f0R-010fbfE-8fc77eS-6f98efR","importSettings":{},"ver":"1","dependencies":["3e39f0R-af5af9E-882fb4S-35be2eR"],"fileDependencies":["4eabb1F-a6d6acI-18916bL-c22216E"],"size":198,"srcHash":"f02a26edfaea08cd8a2b360c40c3b18e","hash":"f02a26edfaea08cd8a2b360c40c3b18e","service":"defaultService"}},"d4f2ccR-2938e9E-94e807S-be4cd5R":{"path":"d4/d4f2ccR-2938e9E-94e807S-be4cd5R.heavyRes","tempPath":"","meta":{"uuid":"d4f2ccR-2938e9E-94e807S-be4cd5R","importSettings":{},"ver":"1","dependencies":["b0d843R-2c7dbeE-16080dS-63ada6R"],"fileDependencies":["5a7b80F-d1c0a9I-7018cbL-2b13a5E"],"size":188,"srcHash":"72217ee7ac0b6012c0bc139491e7d52f","hash":"72217ee7ac0b6012c0bc139491e7d52f","service":"defaultService"}},"d4f4caR-d6008aE-e8c511S-81b8d1R":{"path":"d4/d4f4caR-d6008aE-e8c511S-81b8d1R.TGA.mat","tempPath":"","meta":{"dependencies":["be1ec9R-485a70E-77aaf6S-f56022R","c7fb21R-abb109E-a8e91bS-54b4baR"],"fileDependencies":[],"uuid":"d4f4caR-d6008aE-e8c511S-81b8d1R","importSettings":{"inheritGroupId":true,"groupId":"","isEntries":"false","recursiveSetEntries":true,"isPackInBuildIn":"false"},"ver":"1","size":427,"service":"defaultService","hash":"10db36bc2870d61a9fce28339ee5446d","srcHash":"10db36bc2870d61a9fce28339ee5446d"}},"d5b210R-110eaeE-1f8b8dS-9d3767R":{"path":"d5/d5b210R-110eaeE-1f8b8dS-9d3767R.spriteframe","tempPath":"","meta":{"uuid":"d5b210R-110eaeE-1f8b8dS-9d3767R","importSettings":{"isEntries":"false","inheritGroupId":true,"groupId":"","recursiveSetEntries":true,"isPackInBuildIn":"false"},"ver":"1","size":45,"service":"defaultService","hash":"740fc417eda24ae2b87ea40c79ed9cb6","dependencies":["eb5df0R-ec8261E-ec8a94S-2dfd26R"],"fileDependencies":[],"srcHash":"740fc417eda24ae2b87ea40c79ed9cb6"}},"d73f52F-772699I-9ae934L-30c2e1E":{"path":"d7/d73f52F-772699I-9ae934L-30c2e1E.png","tempPath":"","meta":{"uuid":"d73f52F-772699I-9ae934L-30c2e1E","hash":"55c3188f33d05dc44c9c81000774492a","srcHash":"55c3188f33d05dc44c9c81000774492a","importSettings":{"textureData":{"data":{"width":256,"height":256,"sRGB":true,"needPremultiplyAlpha":false,"useMipmap":true,"mipmap":9,"wrapU":1,"wrapV":1,"filterMode":2,"pixelFormat":2,"anisoLevel":1},"editorInfo":{"assetVersion":2,"enableCompress":true}},"__localId":{"texture2d":1},"metaMTime":1604661025956,"inheritGroupId":true,"groupId":"","isEntries":"false","recursiveSetEntries":true,"isPackInBuildIn":"false"},"dependencies":[],"fileDependencies":[],"size":38177,"service":"defaultService"}},"d940aaR-c8216aE-1ddd26S-cd8066R":{"path":"d9/d940aaR-c8216aE-1ddd26S-cd8066R.heavyRes","tempPath":"","meta":{"uuid":"d940aaR-c8216aE-1ddd26S-cd8066R","importSettings":{},"ver":"1","dependencies":["894015R-3f2fd8E-9fcebcS-6a181fR"],"fileDependencies":["0afeedF-26b84aI-dfda01L-b682c6E"],"size":190,"srcHash":"4b6ffcf8a89754d3193bd31dd3d2ea91","hash":"4b6ffcf8a89754d3193bd31dd3d2ea91","service":"defaultService"}},"df6f5aR-6fbfeaE-0bfd4dS-2c1c6cR":{"path":"df/df6f5aR-6fbfeaE-0bfd4dS-2c1c6cR.effect","tempPath":"","meta":{"uuid":"df6f5aR-6fbfeaE-0bfd4dS-2c1c6cR","importSettings":{"inheritGroupId":true,"groupId":"","isEntries":"true","recursiveSetEntries":true,"isPackInBuildIn":"true"},"dependencies":[],"fileDependencies":[],"size":2371,"service":"defaultService","srcHash":"a679729e9dd5b727f7132c3818d5fc28","hash":"a679729e9dd5b727f7132c3818d5fc28"}},"e12986F-a034aaI-4ed379L-e9f86fE":{"path":"e1/e12986F-a034aaI-4ed379L-e9f86fE.bin","tempPath":"","meta":{"uuid":"e12986F-a034aaI-4ed379L-e9f86fE","importSettings":{"relatedSrcUuid":"a58ceaR-3e3505E-6029d5S-8e6761R"},"ver":"1","dependencies":[],"fileDependencies":[],"size":24,"hash":"04e2f69e92e27fe6b8834deb00d41de6","srcHash":"04e2f69e92e27fe6b8834deb00d41de6","service":"defaultService"}},"e243c4F-e773dfI-1f03ccL-ef8048E":{"path":"e2/e243c4F-e773dfI-1f03ccL-ef8048E.jpg","tempPath":"","meta":{"uuid":"e243c4F-e773dfI-1f03ccL-ef8048E","hash":"8612a0aadf378570c33e41e58afe29da","srcHash":"8612a0aadf378570c33e41e58afe29da","importSettings":{"textureData":{"data":{"width":512,"height":512,"sRGB":true,"needPremultiplyAlpha":false,"useMipmap":true,"mipmap":10,"wrapU":1,"wrapV":1,"filterMode":2,"pixelFormat":2,"anisoLevel":1},"editorInfo":{"assetVersion":2,"enableCompress":true}},"__localId":{"texture2d":1},"metaMTime":1604661026008,"inheritGroupId":true,"groupId":"","isEntries":"false","recursiveSetEntries":true,"isPackInBuildIn":"false"},"dependencies":[],"fileDependencies":[],"size":25951,"service":"defaultService"}},"e2931cR-e5d63dE-13ccc4S-7a797dR":{"path":"e2/e2931cR-e5d63dE-13ccc4S-7a797dR.effect","tempPath":"","meta":{"uuid":"e2931cR-e5d63dE-13ccc4S-7a797dR","importSettings":{"inheritGroupId":true,"groupId":"","isEntries":"true","recursiveSetEntries":true,"isPackInBuildIn":"true"},"dependencies":[],"fileDependencies":[],"size":1443,"service":"defaultService","srcHash":"399df3f87eb8398b474f664cc230123d","hash":"399df3f87eb8398b474f664cc230123d"}},"e7c289R-deed1dE-bf6bf1S-491b08R":{"path":"e7/e7c289R-deed1dE-bf6bf1S-491b08R.heavyRes","tempPath":"","meta":{"uuid":"e7c289R-deed1dE-bf6bf1S-491b08R","importSettings":{},"ver":"1","dependencies":["23502aR-daafd4E-57b165S-101c8bR"],"fileDependencies":["d73f52F-772699I-9ae934L-30c2e1E"],"size":190,"srcHash":"8131a92547d2db1580ddf21639806bb9","hash":"8131a92547d2db1580ddf21639806bb9","service":"defaultService"}},"e82611R-d614fcE-a264f9S-47a5faR":{"path":"e8/e82611R-d614fcE-a264f9S-47a5faR.heavyRes","tempPath":"","meta":{"uuid":"e82611R-d614fcE-a264f9S-47a5faR","importSettings":{},"ver":"1","dependencies":["c5d410R-b8a879E-2599bcS-5680ddR"],"fileDependencies":["0a74a6F-e91e17I-33a59bL-16e923E"],"size":198,"srcHash":"cd05fb07356d39d8ab274534cf683c2c","hash":"cd05fb07356d39d8ab274534cf683c2c","service":"defaultService"}},"ec27ccR-ba688fE-364978S-923276R":{"path":"ec/ec27ccR-ba688fE-364978S-923276R.effect","tempPath":"","meta":{"uuid":"ec27ccR-ba688fE-364978S-923276R","importSettings":{"inheritGroupId":true,"groupId":"","isEntries":"true","recursiveSetEntries":true,"isPackInBuildIn":"true"},"dependencies":[],"fileDependencies":[],"size":2185,"service":"defaultService","srcHash":"cabebe05ebab937dd4032c8465f97cbf","hash":"cabebe05ebab937dd4032c8465f97cbf"}},"eca7b9R-2737f8E-ac8050S-d327c0R":{"path":"ec/eca7b9R-2737f8E-ac8050S-d327c0R.heavyRes","tempPath":"","meta":{"uuid":"eca7b9R-2737f8E-ac8050S-d327c0R","importSettings":{},"ver":"1","dependencies":["1fe445R-5afe4eE-682922S-fe7185R"],"fileDependencies":["e243c4F-e773dfI-1f03ccL-ef8048E"],"size":194,"srcHash":"9b6b7cdafa0c9ed373fad37fff3e582f","hash":"9b6b7cdafa0c9ed373fad37fff3e582f","service":"defaultService"}},"f1c742R-b8cfa1E-d89a37S-69a5f6R":{"path":"f1/f1c742R-b8cfa1E-d89a37S-69a5f6R.mat","tempPath":"","meta":{"uuid":"f1c742R-b8cfa1E-d89a37S-69a5f6R","importSettings":{"inheritGroupId":true,"groupId":"","isEntries":"false","recursiveSetEntries":true,"isPackInBuildIn":"false"},"ver":"1","size":486,"service":"defaultService","hash":"2e29911fd1975263c66612c3b7625854","dependencies":["342acdR-3ac821E-9f6ae5S-63fba6R","c7fb21R-abb109E-a8e91bS-54b4baR"],"fileDependencies":[],"srcHash":"2e29911fd1975263c66612c3b7625854"}},"f490b7F-c850f8I-8fb042L-320b34E":{"path":"f4/f490b7F-c850f8I-8fb042L-320b34E.bin","tempPath":"","meta":{"uuid":"f490b7F-c850f8I-8fb042L-320b34E","importSettings":{"relatedSrcUuid":"54c366R-18c89dE-201764S-f4ffb9R"},"ver":"1","dependencies":[],"fileDependencies":[],"size":584,"hash":"467a8768ab50e46f26c46a3ef96177a1","srcHash":"467a8768ab50e46f26c46a3ef96177a1","service":"defaultService"}},"f5b812R-5145f6E-2d6b53S-5faf60R":{"path":"f5/f5b812R-5145f6E-2d6b53S-5faf60R.heavyRes","tempPath":"","meta":{"uuid":"f5b812R-5145f6E-2d6b53S-5faf60R","importSettings":{},"ver":"1","dependencies":["a1c543R-06b0b6E-2320a5S-ea08fbR"],"fileDependencies":["bc8d98F-b4e368I-92bb6dL-8d40d5E"],"size":198,"srcHash":"0d864541c8e0774fae851e1f977780f1","hash":"0d864541c8e0774fae851e1f977780f1","service":"defaultService"}},"f6a545R-2aea9fE-e838f8S-df63ecR":{"path":"f6/f6a545R-2aea9fE-e838f8S-df63ecR.heavyRes","tempPath":"","meta":{"uuid":"f6a545R-2aea9fE-e838f8S-df63ecR","importSettings":{},"ver":"1","dependencies":["a3b552R-3ab22fE-1af925S-17deb8R"],"fileDependencies":["a9dadbF-357f88I-e647caL-128c85E"],"size":198,"srcHash":"eec5cd4211f538fc73c880508b679182","hash":"eec5cd4211f538fc73c880508b679182","service":"defaultService"}},"f75b6eR-26db4aE-74d251S-b121f3R":{"path":"f7/f75b6eR-26db4aE-74d251S-b121f3R.effect","tempPath":"","meta":{"uuid":"f75b6eR-26db4aE-74d251S-b121f3R","importSettings":{"inheritGroupId":true,"groupId":"","isEntries":"false","recursiveSetEntries":true,"isPackInBuildIn":"false"},"dependencies":[],"fileDependencies":[],"size":128129,"service":"defaultService","srcHash":"3a7ecad323901fe8286afe5ada8a5395","hash":"3a7ecad323901fe8286afe5ada8a5395"}},"f80ec5R-e5ae6fE-ca3bd1S-f29f09R":{"path":"f8/f80ec5R-e5ae6fE-ca3bd1S-f29f09R.mesh","tempPath":"","meta":{"uuid":"f80ec5R-e5ae6fE-ca3bd1S-f29f09R","importSettings":{"inheritGroupId":true,"groupId":"","isEntries":"false","recursiveSetEntries":true,"isPackInBuildIn":"false"},"ver":"1","size":378,"service":"defaultService","hash":"3e07a5fd124f948f5a7bae445b59c599","dependencies":[],"fileDependencies":["1e502eF-4e6cbbI-b9ecabL-e1e51cE"],"srcHash":"3e07a5fd124f948f5a7bae445b59c599"}},"fd6f7bR-35ebafE-aa4f88S-6f3ef3R":{"path":"fd/fd6f7bR-35ebafE-aa4f88S-6f3ef3R.heavyRes","tempPath":"","meta":{"uuid":"fd6f7bR-35ebafE-aa4f88S-6f3ef3R","importSettings":{},"ver":"1","dependencies":["3e39f0R-af5af9E-882fb4S-35be2eR"],"fileDependencies":["4eabb1F-a6d6acI-18916bL-c22216E"],"size":194,"srcHash":"604c9f0054f45f2cd42e30ffcf9ad7eb","hash":"604c9f0054f45f2cd42e30ffcf9ad7eb","service":"defaultService"}}}}
